Workbook

Sheet Start Here
B2: TALENT POOL SYSTEM · FREE DEMO
B3: Candidate Talent Pool
B4: Recruit • Learn • Store • Reuse
B5: Turn every candidate you meet into an asset for your next vacancy.
B8: Licensed software. Single-company use, up to 5 users. No resale or redistribution. Full license at the bottom of this page ↓
B9: CREATED BY | I9: WANT FULL ACCESS?
B10: =Settings!B2 -> Mohammad Zargar | I10: This is a view-only demo. Message me and I will give you full access, so you can add candidates, log follow-ups and test it with your own data.
B11: =Settings!B3 -> Process Improvement & Business Systems
B12: =HYPERLINK(IF(LEFT(Settings!B4,4)="http",Settings!B4,"https://"&Settings!B4),"💼 LinkedIn: "&SUBSTITUTE(SUBSTITUTE(Settings!B4,"https://",""),"www.","")) -> 💼 LinkedIn: linkedin.com/mohammad-zargar
B13: =HYPERLINK("mailto:"&Settings!B5,"✉️ Email: "&Settings!B5) -> ✉️ Email: s.mohammad.zargar@gmail.com | J13: =HYPERLINK("mailto:"&Settings!B5&"?subject="&SUBSTITUTE(Settings!B6," ","%20"),"Request full access →") -> Request full access →
B16: WHAT IT DOES
B17: 🗂️ | F17: 🔎 | J17: 🔔
B18: Remember everyone | F18: Find matches in seconds | J18: Never miss a follow-up
B19: Every candidate you meet is saved with skills, status and consent, hired or not. | F19: Pick a vacancy and get a ranked list of people you already know, scored out of 100. | J19: See who to contact today or tomorrow and log every conversation in one place.
B21: GET STARTED IN 3 STEPS
B22: 1 | F22: 2 | J22: 3
B23: Add | F23: Find | J23: Follow up
B24: After each hiring round, register every candidate in the Add Candidate tab. | F24: When a position opens, pick it in Find Candidates and see the best matches. | J24: Log every contact in Follow-Up and watch the Dashboard.
B26: TABS AT A GLANCE
B27: 📊 Dashboard | E27: Candidates recorded, hired, open positions, who to contact today or tomorrow, plus charts.
B28: ➕ Add Candidate | E28: The form you use to register a candidate.
B29: 🗂️ Candidates | E29: The database. One row per candidate, with colors for status and future potential.
B30: 🔔 Follow-Up 🔒 | E30: 🔒 Premium. Log every contact with a candidate, and see who is due to be contacted next.
B31: 🔎 Find Candidates 🔒 | E31: 🔒 Premium. Pick a vacancy and get a ranked list of past candidates who may fit.
B32: 📌 Positions | E32: Your job positions: status (Open, On Hold, Closed), openings, hiring manager, requirements.
B33: 📝 Contact Log 🔒 | E33: 🔒 Premium. The history of every follow-up. Filled automatically.
B34: 📋 Lists | E34: The values behind the dropdown menus (skills, statuses, cities).
B36: Full instructions
B37: Everything you need to use the workbook, step by step.
B38: A. ADD A CANDIDATE (about 1 minute)
B39: Step 1 | E39: Open the Add Candidate tab.
B40: Step 2 | E40: Fill in the yellow cells from top to bottom. Use the dropdown arrows wherever you see one. Required fields are marked in the hint column.
B41: Step 3 | E41: Click the ADD CANDIDATE button (or the menu Talent Pool > Add candidate).
B42: Step 4 | E42: The form clears and the candidate appears at the bottom of the Candidates tab with an ID like CAN-2026-00041.
B43: Good to know | E43: Recruitment status is what happened in this hiring round. Future potential is whether you would consider this person for a different role later. Someone who was Not Selected can still be a Strong Future Fit.
B44: Consent | E44: Choose Yes only if the candidate agreed to be kept in your talent pool. Candidates without consent never appear in match results.
B46: B. MANAGE JOB POSITIONS
B47: Step 1 | E47: Open the Positions tab. Each row is one job position with its department, location, salary budget, required skills, status, number of openings, date opened, hiring manager and priority.
B48: Step 2 | E48: To add a position, fill in the next empty row (up to row 51). Use the dropdowns for Status and Priority.
B49: Status | E49: Open = you are hiring now. On Hold = paused. Closed = filled or cancelled. Only Open positions are counted on the Dashboard.
B50: Openings | E50: How many people you want to hire for that position. The Dashboard adds them up as openings to fill.
B52: C. FIND CANDIDATES FOR A NEW VACANCY
B53: Step 1 | E53: Open the Find Candidates tab.
B54: Step 2 | E54: Choose the position in the yellow cell at the top. The department, minimum experience, location, budget and required skills appear automatically.
B55: Step 3 | E55: Read the Top 10 list. Each person has a score out of 100, a bar, a rating, and the points they earned for each criterion.
B56: Ratings | E56: 70 or more = Strong match. 50 to 69 = Possible match. Below 50 = Weak match.
B57: Step 4 | E57: Contact the best candidates, then record the contact in the Follow-Up tab.
B58: New job type? | E58: Add a row in the Positions tab. It appears in the dropdown right away.
B60: D. HOW THE SCORE WORKS (you never type the score)
B61: Skills (40) | E61: The share of the required skills the candidate has. Having 4 of 5 required skills earns 80% of the 40 points.
B62: Experience (25) | E62: Full points if the candidate has at least the minimum years. Fewer years earns a proportion of the points.
B63: Department (15) | E63: Full points if the candidate applied in the same department as this vacancy.
B64: Location (10) | E64: Full points if the candidate is in the same city as the job.
B65: Availability (5) | E65: Full points if they can start within 30 days, half the points within 60 days.
B66: Salary (5) | E66: Full points if their expected salary is at or below the budget.
B67: Who is excluded | E67: People with status Hired, people marked Do Not Contact, and people without consent are never shown.
B68: Customize | E68: You can change the points in the yellow cells on Find Candidates. Keep the total at 100.
B69: Important | E69: The score helps a recruiter decide who to review first. It does not decide who gets hired. A person always makes the final decision.
B71: E. LOG A FOLLOW-UP
B72: Step 1 | E72: Open the Follow-Up tab. Part B lists who is due within 30 days. Overdue contacts are in red.
B73: Step 2 | E73: In Part A, pick the candidate from the dropdown. Check that the name shown below it is the right person.
B74: Step 3 | E74: Enter the date you contacted them (MM/DD/YYYY) and choose the outcome. Add a note and a next follow-up date if needed.
B75: Step 4 | E75: Click the SAVE FOLLOW-UP button (or the menu Talent Pool > Save follow-up).
B76: Outcomes | E76: Interested and No response: they stay in the pool and the next follow-up date is updated. Hired elsewhere: follow-up is cleared unless you enter a new date. Not interested: marked as not interested in future roles and removed from follow-up. Do not contact again: marked Do Not Contact and excluded from all matching.
B77: Result | E77: The candidate row is updated and a line is added to the Contact Log tab.
B79: F. READ THE DASHBOARD
B80: Candidates recorded | E80: How many candidates are registered in the Candidates tab.
B81: Accepted (hired) | E81: Candidates whose recruitment status is Hired, and their share of all candidates.
B82: Open positions | E82: Positions with status Open, and the total number of openings to fill.
B83: Due today or tomorrow | E83: Names of candidates whose next follow-up date is today or tomorrow, with a Today or Tomorrow label and how strong a future fit they are. Contact them, then log it in the Follow-Up tab.
B84: Open positions list | E84: Each open position with its location, openings and days open (days turn red after 30).
B85: Charts | E85: Recruitment pipeline, future potential, candidates by department, and follow-ups by month. They update by themselves.
B87: G. CUSTOMIZE AND LIMITS
B88: Dropdown lists | E88: Edit the Lists tab to add skills, cities, sources or statuses. Add new skills at the bottom of the Skills column.
B89: Capacity | E89: The workbook is built for up to 200 candidates and 50 positions.
B90: Buttons | E90: The buttons and the Talent Pool menu need edit access. The first time you use them, Google asks for permission: choose your account, then Advanced, then Go to the project, then Allow. This is normal for personal scripts.
B91: Demo data | E91: Every name, email and number in this file is fictional. Several demo follow-up dates are tied to today's date so the Due today or tomorrow list always shows examples. Delete the sample rows in Candidates and Positions before using it with real people.
B93: H. PRIVACY AND GOOD PRACTICE
B94: Keep it minimal | E94: Store only what you need to evaluate candidates for jobs. Do not store Social Security numbers, birth dates, or information about protected characteristics (for example race, religion, age, disability or family status).
B95: Consent | E95: Keep candidate data only with their consent and follow your company policy and applicable laws. This prototype is not legal advice.
B97: I. TROUBLESHOOTING
B98: Script function could not be found | E98: The button is assigned to a script name that does not match. Use exactly addCandidate or saveFollowUp (capital letters matter).
B99: The match list is empty | E99: No eligible candidates. Check that candidates have consent = Yes and are not Hired or Do Not Contact.
B100: A dropdown is empty or has no value I need | E100: Add the value in the Lists tab (or Positions tab for positions).
B101: Numbers look wrong | E101: Dates must be real dates (MM/DD/YYYY) and salary must be a plain number.
B103: Candidate Talent Pool · View-only demo · All names and data are fictional
B105: 📜 LICENSE
B106: ="Licensed to: "&Settings!B7&" · Licensor: "&Settings!B2&" · "&Settings!B5 -> Licensed to: Demo copy, not licensed for business use · Licensor: Mohammad Zargar · s.mohammad.zargar@gmail.com
B107: 1. Grant | D107: The Licensor (the creator named above) grants you a non-exclusive, non-transferable license to use this workbook and its script for the internal recruiting work of ONE company or organization.
B108: 2. Users | D108: One license covers up to 5 named users (email addresses) within that company.
B109: 3. Not allowed | D109: Reselling, sharing, publishing, sublicensing or distributing this workbook, in whole or in part, to anyone outside your license. Removing this notice or the creator's name is not allowed.
B110: 4. Your data | D110: Your candidate data stays yours. The Licensor does not receive it. You are responsible for storing it lawfully and with candidate consent.
B111: 5. Ownership | D111: The design, formulas, scoring method and script remain the intellectual property of the Licensor. You may modify your own copy for internal use.
B112: 6. No warranty | D112: Provided 'as is', without warranty. The match score supports a recruiter's review and never replaces a human hiring decision. The Licensor is not liable for hiring decisions or data loss.
B113: 7. Termination | D113: The license ends automatically if you break these terms.
B114: Note | D114: This is a summary template, not legal advice. Have a lawyer review it before relying on it.

Sheet Dashboard
A1: Dashboard
A2: Your talent pool at a glance. Recruit, learn, store, reuse.
A4: 👥 CANDIDATES RECORDED | D4: ✅ ACCEPTED (HIRED) | G4: 📌 OPEN POSITIONS | J4: ⏰ DUE TODAY OR TOMORROW
A5: =COUNTA(Candidates!$A$2:$A$201) -> 40 | D5: =COUNTIF(Candidates!$M$2:$M$201,"Hired") -> 5 | G5: =COUNTIF(Positions!$L$2:$L$51,"Open") -> 6 | J5: =COUNTIF(Candidates!$X$2:$X$201,1)+COUNTIF(Candidates!$X$2:$X$201,2) -> 5
A7: in the talent pool | D7: ="Hired = "&IF(COUNTA(Candidates!$A$2:$A$201)=0,"0%",TEXT(COUNTIF(Candidates!$M$2:$M$201,"Hired")/COUNTA(Candidates!$A$2:$A$201),"0%"))&" of all candidates" -> Hired = 13% of all candidates | G7: =SUMIF(Positions!$L$2:$L$51,"Open",Positions!$M$2:$M$51)&" openings to fill" -> 10 openings to fill | J7: ="Today: "&COUNTIF(Candidates!$X$2:$X$201,1)&" | Tomorrow: "&COUNTIF(Candidates!$X$2:$X$201,2) -> Today: 2 | Tomorrow: 3
A9: 📌 OPEN POSITIONS | G9: ⏰ FOLLOW-UP DUE TODAY OR TOMORROW
A10: Position | Department | D10: Location | E10: Openings | F10: Days open | G10: Candidate | I10: Applied for | K10: Due | L10: Future fit
A11: =IFERROR(INDEX(Positions!$C$2:$C$51,MATCH(1,Positions!$Q$2:$Q$51,0))&" | "&INDEX(Positions!$B$2:$B$51,MATCH(1,Positions!$Q$2:$Q$51,0)),IF(1=1,"No open positions","")) -> Operations Manager | Operations | D11: =IFERROR(INDEX(Positions!$E$2:$E$51,MATCH(1,Positions!$Q$2:$Q$51,0)),"") -> Chicago, IL | E11: =IFERROR(INDEX(Positions!$M$2:$M$51,MATCH(1,Positions!$Q$2:$Q$51,0)),"") -> 1 | F11: =IFERROR(TODAY()-INDEX(Positions!$N$2:$N$51,MATCH(1,Positions!$Q$2:$Q$51,0)),"") -> 27 | G11: =IFERROR(INDEX(Candidates!$C$2:$C$201,MATCH(1,Candidates!$Y$2:$Y$201,0)),IF(1=1,"Nobody is due today or tomorrow","")) -> Jessica Miller | I11: =IFERROR(INDEX(Candidates!$E$2:$E$201,MATCH(1,Candidates!$Y$2:$Y$201,0)),"") -> Quality Engineer | K11: =IFERROR(IF(INDEX(Candidates!$X$2:$X$201,MATCH(1,Candidates!$Y$2:$Y$201,0))=1,"Today","Tomorrow"),"") -> Today | L11: =IFERROR(IF(INDEX(Candidates!$N$2:$N$201,MATCH(1,Candidates!$Y$2:$Y$201,0))="Strong Future Fit","Strong","Potential"),"") -> Potential
A12: =IFERROR(INDEX(Positions!$C$2:$C$51,MATCH(2,Positions!$Q$2:$Q$51,0))&" | "&INDEX(Positions!$B$2:$B$51,MATCH(2,Positions!$Q$2:$Q$51,0)),IF(2=1,"No open positions","")) -> Data Analyst | Analytics | D12: =IFERROR(INDEX(Positions!$E$2:$E$51,MATCH(2,Positions!$Q$2:$Q$51,0)),"") -> Austin, TX | E12: =IFERROR(INDEX(Positions!$M$2:$M$51,MATCH(2,Positions!$Q$2:$Q$51,0)),"") -> 2 | F12: =IFERROR(TODAY()-INDEX(Positions!$N$2:$N$51,MATCH(2,Positions!$Q$2:$Q$51,0)),"") -> 20 | G12: =IFERROR(INDEX(Candidates!$C$2:$C$201,MATCH(2,Candidates!$Y$2:$Y$201,0)),IF(2=1,"Nobody is due today or tomorrow","")) -> Jessica Thomas | I12: =IFERROR(INDEX(Candidates!$E$2:$E$201,MATCH(2,Candidates!$Y$2:$Y$201,0)),"") -> Marketing Manager | K12: =IFERROR(IF(INDEX(Candidates!$X$2:$X$201,MATCH(2,Candidates!$Y$2:$Y$201,0))=1,"Today","Tomorrow"),"") -> Today | L12: =IFERROR(IF(INDEX(Candidates!$N$2:$N$201,MATCH(2,Candidates!$Y$2:$Y$201,0))="Strong Future Fit","Strong","Potential"),"") -> Potential
A13: =IFERROR(INDEX(Positions!$C$2:$C$51,MATCH(3,Positions!$Q$2:$Q$51,0))&" | "&INDEX(Positions!$B$2:$B$51,MATCH(3,Positions!$Q$2:$Q$51,0)),IF(3=1,"No open positions","")) -> HR Generalist | Human Resources | D13: =IFERROR(INDEX(Positions!$E$2:$E$51,MATCH(3,Positions!$Q$2:$Q$51,0)),"") -> Atlanta, GA | E13: =IFERROR(INDEX(Positions!$M$2:$M$51,MATCH(3,Positions!$Q$2:$Q$51,0)),"") -> 1 | F13: =IFERROR(TODAY()-INDEX(Positions!$N$2:$N$51,MATCH(3,Positions!$Q$2:$Q$51,0)),"") -> 13 | G13: =IFERROR(INDEX(Candidates!$C$2:$C$201,MATCH(3,Candidates!$Y$2:$Y$201,0)),IF(3=1,"Nobody is due today or tomorrow","")) -> Jessica Anderson | I13: =IFERROR(INDEX(Candidates!$E$2:$E$201,MATCH(3,Candidates!$Y$2:$Y$201,0)),"") -> Quality Engineer | K13: =IFERROR(IF(INDEX(Candidates!$X$2:$X$201,MATCH(3,Candidates!$Y$2:$Y$201,0))=1,"Today","Tomorrow"),"") -> Tomorrow | L13: =IFERROR(IF(INDEX(Candidates!$N$2:$N$201,MATCH(3,Candidates!$Y$2:$Y$201,0))="Strong Future Fit","Strong","Potential"),"") -> Potential
A14: =IFERROR(INDEX(Positions!$C$2:$C$51,MATCH(4,Positions!$Q$2:$Q$51,0))&" | "&INDEX(Positions!$B$2:$B$51,MATCH(4,Positions!$Q$2:$Q$51,0)),IF(4=1,"No open positions","")) -> Account Executive | Sales | D14: =IFERROR(INDEX(Positions!$E$2:$E$51,MATCH(4,Positions!$Q$2:$Q$51,0)),"") -> Dallas, TX | E14: =IFERROR(INDEX(Positions!$M$2:$M$51,MATCH(4,Positions!$Q$2:$Q$51,0)),"") -> 3 | F14: =IFERROR(TODAY()-INDEX(Positions!$N$2:$N$51,MATCH(4,Positions!$Q$2:$Q$51,0)),"") -> 34 | G14: =IFERROR(INDEX(Candidates!$C$2:$C$201,MATCH(4,Candidates!$Y$2:$Y$201,0)),IF(4=1,"Nobody is due today or tomorrow","")) -> Megan Martin | I14: =IFERROR(INDEX(Candidates!$E$2:$E$201,MATCH(4,Candidates!$Y$2:$Y$201,0)),"") -> Quality Engineer | K14: =IFERROR(IF(INDEX(Candidates!$X$2:$X$201,MATCH(4,Candidates!$Y$2:$Y$201,0))=1,"Today","Tomorrow"),"") -> Tomorrow | L14: =IFERROR(IF(INDEX(Candidates!$N$2:$N$201,MATCH(4,Candidates!$Y$2:$Y$201,0))="Strong Future Fit","Strong","Potential"),"") -> Potential
A15: =IFERROR(INDEX(Positions!$C$2:$C$51,MATCH(5,Positions!$Q$2:$Q$51,0))&" | "&INDEX(Positions!$B$2:$B$51,MATCH(5,Positions!$Q$2:$Q$51,0)),IF(5=1,"No open positions","")) -> Marketing Manager | Marketing | D15: =IFERROR(INDEX(Positions!$E$2:$E$51,MATCH(5,Positions!$Q$2:$Q$51,0)),"") -> Denver, CO | E15: =IFERROR(INDEX(Positions!$M$2:$M$51,MATCH(5,Positions!$Q$2:$Q$51,0)),"") -> 1 | F15: =IFERROR(TODAY()-INDEX(Positions!$N$2:$N$51,MATCH(5,Positions!$Q$2:$Q$51,0)),"") -> 6 | G15: =IFERROR(INDEX(Candidates!$C$2:$C$201,MATCH(5,Candidates!$Y$2:$Y$201,0)),IF(5=1,"Nobody is due today or tomorrow","")) -> Jason White | I15: =IFERROR(INDEX(Candidates!$E$2:$E$201,MATCH(5,Candidates!$Y$2:$Y$201,0)),"") -> Staff Accountant | K15: =IFERROR(IF(INDEX(Candidates!$X$2:$X$201,MATCH(5,Candidates!$Y$2:$Y$201,0))=1,"Today","Tomorrow"),"") -> Tomorrow | L15: =IFERROR(IF(INDEX(Candidates!$N$2:$N$201,MATCH(5,Candidates!$Y$2:$Y$201,0))="Strong Future Fit","Strong","Potential"),"") -> Potential
A16: =IFERROR(INDEX(Positions!$C$2:$C$51,MATCH(6,Positions!$Q$2:$Q$51,0))&" | "&INDEX(Positions!$B$2:$B$51,MATCH(6,Positions!$Q$2:$Q$51,0)),IF(6=1,"No open positions","")) -> Software Engineer | Engineering | D16: =IFERROR(INDEX(Positions!$E$2:$E$51,MATCH(6,Positions!$Q$2:$Q$51,0)),"") -> Austin, TX | E16: =IFERROR(INDEX(Positions!$M$2:$M$51,MATCH(6,Positions!$Q$2:$Q$51,0)),"") -> 2 | F16: =IFERROR(TODAY()-INDEX(Positions!$N$2:$N$51,MATCH(6,Positions!$Q$2:$Q$51,0)),"") -> 18 | G16: =IFERROR(INDEX(Candidates!$C$2:$C$201,MATCH(6,Candidates!$Y$2:$Y$201,0)),IF(6=1,"Nobody is due today or tomorrow","")) | I16: =IFERROR(INDEX(Candidates!$E$2:$E$201,MATCH(6,Candidates!$Y$2:$Y$201,0)),"") | K16: =IFERROR(IF(INDEX(Candidates!$X$2:$X$201,MATCH(6,Candidates!$Y$2:$Y$201,0))=1,"Today","Tomorrow"),"") | L16: =IFERROR(IF(INDEX(Candidates!$N$2:$N$201,MATCH(6,Candidates!$Y$2:$Y$201,0))="Strong Future Fit","Strong","Potential"),"")
A17: =IFERROR(INDEX(Positions!$C$2:$C$51,MATCH(7,Positions!$Q$2:$Q$51,0))&" | "&INDEX(Positions!$B$2:$B$51,MATCH(7,Positions!$Q$2:$Q$51,0)),IF(7=1,"No open positions","")) | D17: =IFERROR(INDEX(Positions!$E$2:$E$51,MATCH(7,Positions!$Q$2:$Q$51,0)),"") | E17: =IFERROR(INDEX(Positions!$M$2:$M$51,MATCH(7,Positions!$Q$2:$Q$51,0)),"") | F17: =IFERROR(TODAY()-INDEX(Positions!$N$2:$N$51,MATCH(7,Positions!$Q$2:$Q$51,0)),"") | G17: =IFERROR(INDEX(Candidates!$C$2:$C$201,MATCH(7,Candidates!$Y$2:$Y$201,0)),IF(7=1,"Nobody is due today or tomorrow","")) | I17: =IFERROR(INDEX(Candidates!$E$2:$E$201,MATCH(7,Candidates!$Y$2:$Y$201,0)),"") | K17: =IFERROR(IF(INDEX(Candidates!$X$2:$X$201,MATCH(7,Candidates!$Y$2:$Y$201,0))=1,"Today","Tomorrow"),"") | L17: =IFERROR(IF(INDEX(Candidates!$N$2:$N$201,MATCH(7,Candidates!$Y$2:$Y$201,0))="Strong Future Fit","Strong","Potential"),"")
A18: =IFERROR(INDEX(Positions!$C$2:$C$51,MATCH(8,Positions!$Q$2:$Q$51,0))&" | "&INDEX(Positions!$B$2:$B$51,MATCH(8,Positions!$Q$2:$Q$51,0)),IF(8=1,"No open positions","")) | D18: =IFERROR(INDEX(Positions!$E$2:$E$51,MATCH(8,Positions!$Q$2:$Q$51,0)),"") | E18: =IFERROR(INDEX(Positions!$M$2:$M$51,MATCH(8,Positions!$Q$2:$Q$51,0)),"") | F18: =IFERROR(TODAY()-INDEX(Positions!$N$2:$N$51,MATCH(8,Positions!$Q$2:$Q$51,0)),"") | G18: =IFERROR(INDEX(Candidates!$C$2:$C$201,MATCH(8,Candidates!$Y$2:$Y$201,0)),IF(8=1,"Nobody is due today or tomorrow","")) | I18: =IFERROR(INDEX(Candidates!$E$2:$E$201,MATCH(8,Candidates!$Y$2:$Y$201,0)),"") | K18: =IFERROR(IF(INDEX(Candidates!$X$2:$X$201,MATCH(8,Candidates!$Y$2:$Y$201,0))=1,"Today","Tomorrow"),"") | L18: =IFERROR(IF(INDEX(Candidates!$N$2:$N$201,MATCH(8,Candidates!$Y$2:$Y$201,0))="Strong Future Fit","Strong","Potential"),"")
A19: =IF(COUNTIF(Positions!$L$2:$L$51,"Open")>8,"+ "&(COUNTIF(Positions!$L$2:$L$51,"Open")-8)&" more in the Positions tab","") | G19: =IF(COUNTIF(Candidates!$X$2:$X$201,1)+COUNTIF(Candidates!$X$2:$X$201,2)>8,"+ more in the Follow-Up tab","")
A56: Data behind the charts (automatic, do not edit)
A57: Status | B57: Count | D57: Future potential | E57: Count | G57: Department | H57: Count | J57: Follow-ups | K57: Count
A58: Applied | B58: =COUNTIF(Candidates!$M$2:$M$201,"Applied") -> 0 | D58: Strong Future Fit | E58: =COUNTIF(Candidates!$N$2:$N$201,"Strong Future Fit") -> 8 | G58: Operations | H58: =COUNTIF(Candidates!$F$2:$F$201,"Operations") -> 6 | J58: Overdue | K58: =COUNTIFS(Candidates!$R$2:$R$201,"<"&DATE(YEAR(TODAY()),MONTH(TODAY()),1),Candidates!$P$2:$P$201,"Yes") -> 1
A59: Screened | B59: =COUNTIF(Candidates!$M$2:$M$201,"Screened") -> 4 | D59: Potential Future Fit | E59: =COUNTIF(Candidates!$N$2:$N$201,"Potential Future Fit") -> 14 | G59: Analytics | H59: =COUNTIF(Candidates!$F$2:$F$201,"Analytics") -> 5 | J59: =TEXT(EDATE(DATE(YEAR(TODAY()),MONTH(TODAY()),1),0),"mmm yy") -> Oct 26 | K59: =COUNTIFS(Candidates!$R$2:$R$201,">="&EDATE(DATE(YEAR(TODAY()),MONTH(TODAY()),1),0),Candidates!$R$2:$R$201,"<"&EDATE(EDATE(DATE(YEAR(TODAY()),MONTH(TODAY()),1),0),1),Candidates!$P$2:$P$201,"Yes") -> 12
A60: Interviewed | B60: =COUNTIF(Candidates!$M$2:$M$201,"Interviewed") -> 4 | D60: Not Currently Relevant | E60: =COUNTIF(Candidates!$N$2:$N$201,"Not Currently Relevant") -> 16 | G60: Human Resources | H60: =COUNTIF(Candidates!$F$2:$F$201,"Human Resources") -> 4 | J60: =TEXT(EDATE(DATE(YEAR(TODAY()),MONTH(TODAY()),1),1),"mmm yy") -> Nov 26 | K60: =COUNTIFS(Candidates!$R$2:$R$201,">="&EDATE(DATE(YEAR(TODAY()),MONTH(TODAY()),1),1),Candidates!$R$2:$R$201,"<"&EDATE(EDATE(DATE(YEAR(TODAY()),MONTH(TODAY()),1),1),1),Candidates!$P$2:$P$201,"Yes") -> 0
A61: Offered | B61: =COUNTIF(Candidates!$M$2:$M$201,"Offered") -> 0 | D61: Do Not Contact | E61: =COUNTIF(Candidates!$N$2:$N$201,"Do Not Contact") -> 2 | G61: Finance | H61: =COUNTIF(Candidates!$F$2:$F$201,"Finance") -> 7 | J61: =TEXT(EDATE(DATE(YEAR(TODAY()),MONTH(TODAY()),1),2),"mmm yy") -> Dec 26 | K61: =COUNTIFS(Candidates!$R$2:$R$201,">="&EDATE(DATE(YEAR(TODAY()),MONTH(TODAY()),1),2),Candidates!$R$2:$R$201,"<"&EDATE(EDATE(DATE(YEAR(TODAY()),MONTH(TODAY()),1),2),1),Candidates!$P$2:$P$201,"Yes") -> 8
A62: Hired | B62: =COUNTIF(Candidates!$M$2:$M$201,"Hired") -> 5 | G62: Sales | H62: =COUNTIF(Candidates!$F$2:$F$201,"Sales") -> 3 | J62: =TEXT(EDATE(DATE(YEAR(TODAY()),MONTH(TODAY()),1),3),"mmm yy") -> Jan 27 | K62: =COUNTIFS(Candidates!$R$2:$R$201,">="&EDATE(DATE(YEAR(TODAY()),MONTH(TODAY()),1),3),Candidates!$R$2:$R$201,"<"&EDATE(EDATE(DATE(YEAR(TODAY()),MONTH(TODAY()),1),3),1),Candidates!$P$2:$P$201,"Yes") -> 0
A63: Not Selected | B63: =COUNTIF(Candidates!$M$2:$M$201,"Not Selected") -> 22 | G63: Marketing | H63: =COUNTIF(Candidates!$F$2:$F$201,"Marketing") -> 7 | J63: =TEXT(EDATE(DATE(YEAR(TODAY()),MONTH(TODAY()),1),4),"mmm yy") -> Feb 27 | K63: =COUNTIFS(Candidates!$R$2:$R$201,">="&EDATE(DATE(YEAR(TODAY()),MONTH(TODAY()),1),4),Candidates!$R$2:$R$201,"<"&EDATE(EDATE(DATE(YEAR(TODAY()),MONTH(TODAY()),1),4),1),Candidates!$P$2:$P$201,"Yes") -> 0
A64: Withdrawn | B64: =COUNTIF(Candidates!$M$2:$M$201,"Withdrawn") -> 5 | G64: Engineering | H64: =COUNTIF(Candidates!$F$2:$F$201,"Engineering") -> 8 | J64: =TEXT(EDATE(DATE(YEAR(TODAY()),MONTH(TODAY()),1),5),"mmm yy") -> Mar 27 | K64: =COUNTIFS(Candidates!$R$2:$R$201,">="&EDATE(DATE(YEAR(TODAY()),MONTH(TODAY()),1),5),Candidates!$R$2:$R$201,"<"&EDATE(EDATE(DATE(YEAR(TODAY()),MONTH(TODAY()),1),5),1),Candidates!$P$2:$P$201,"Yes") -> 0

Sheet Add Candidate
A1: Add a Candidate
A2: Step 1: fill the yellow cells. Step 2: click the ADD CANDIDATE button (or menu Talent Pool > Add candidate).
A4: 👤 1. About the candidate
A5: Name | C5: e.g. Jessica Taylor
A6: Contact | C6: e.g. jessica.taylor@email.com or (555) 123-4567
A7: Position applied for | C7: Pick from the list
A8: Department (automatic) | B8: =IFERROR(INDEX(Positions!$B$2:$B$51,MATCH(B7,Positions!$C$2:$C$51,0)),"") | C8: Filled in for you
A10: 🧩 2. Skills and fit
A11: Skill 1 | C11: Pick from the list. Required
A12: Skill 2 | C12: Optional
A13: Skill 3 | C13: Optional
A14: Skill 4 | C14: Optional
A15: Skill 5 | C15: Optional
A16: Years of experience | C16: Whole years, e.g. 4
A17: Expected salary (USD/year) | C17: Annual salary in USD, e.g. 85000
A18: Location | C18: Pick from the list
A19: Notice period (days) | C19: Days until they could start, e.g. 14
A21: 📋 3. Hiring outcome
A22: Source | C22: Where the candidate came from
A23: Recruitment status | C23: What happened in this hiring round
A24: Future potential | C24: Could this person fit a FUTURE role? (separate from status)
A25: Reason for decision | C25: Short note, e.g. Salary above budget
A27: 🔔 4. Future contact
A28: Interested in future roles? | C28: Yes / No
A29: Consent to keep their data? | C29: Must be Yes to be used in matching
A30: Next follow-up date | C30: When to contact them again
A32: Tip: all data in this file is fictional demo data.
A33: Yellow = you type or pick. Grey = automatic.

Sheet Candidates
A1: Candidate ID | B1: Date Added | C1: Name | D1: Contact | E1: Position Applied | F1: Department | G1: Skills | H1: Years of Experience | I1: Expected Salary (USD/year) | J1: Location | K1: Notice Period (days) | L1: Source | M1: Recruitment Status | N1: Future Potential | O1: Reason for Decision | P1: Interested in Future Roles | Q1: Consent to Retain Data | R1: Next Follow-up Date | S1: Last Contact Date | T1: Last Contact Outcome | U1: due (helper) | V1: due # (helper) | W1: label (helper) | X1: today/tomorrow (helper) | Y1: today/tomorrow # (helper)
A2: CAN-2026-00001 | B2: 46086 | C2: Jason Martinez | D2: jason.martinez@example.com | E2: Marketing Manager | F2: Marketing | G2: Google Analytics, SEO, Budgeting | H2: 2 | I2: 110000 | J2: Chicago, IL | K2: 14 | L2: LinkedIn | M2: Withdrawn | N2: Potential Future Fit | O2: Relocation not possible | P2: Yes | Q2: No | R2: 46361 | S2: 46293 | T2: Interested | U2: =IF(A2="","",IF(AND(R2<>"",R2<=TODAY()+30,P2="Yes",Q2="Yes",N2<>"Do Not Contact"),1,0)) -> 0 | V2: =IF(U2=1,COUNTIF($U$2:U2,1),"") | W2: =IF(A2="","",A2&" | "&C2) -> CAN-2026-00001 | Jason Martinez | X2: =IF(A2="","",IF(AND(R2<>"",P2="Yes",Q2="Yes",N2<>"Do Not Contact"),IF(INT(R2)=TODAY(),1,IF(INT(R2)=TODAY()+1,2,0)),0)) -> 0 | Y2: =IF(OR(X2=1,X2=2),COUNTIF($X$2:X2,1)+COUNTIF($X$2:X2,2),"")
A3: CAN-2026-00002 | B3: 46086 | C3: Daniel Jackson | D3: daniel.jackson@example.com | E3: Staff Accountant | F3: Finance | G3: Excel, QuickBooks, Reconciliation, Accounts Payable | H3: 9 | I3: 69000 | J3: Austin, TX | K3: 60 | L3: Indeed | M3: Not Selected | N3: Not Currently Relevant | O3: Insufficient experience for this level | P3: Yes | Q3: No | U3: =IF(A3="","",IF(AND(R3<>"",R3<=TODAY()+30,P3="Yes",Q3="Yes",N3<>"Do Not Contact"),1,0)) -> 0 | V3: =IF(U3=1,COUNTIF($U$2:U3,1),"") | W3: =IF(A3="","",A3&" | "&C3) -> CAN-2026-00002 | Daniel Jackson | X3: =IF(A3="","",IF(AND(R3<>"",P3="Yes",Q3="Yes",N3<>"Do Not Contact"),IF(INT(R3)=TODAY(),1,IF(INT(R3)=TODAY()+1,2,0)),0)) -> 0 | Y3: =IF(OR(X3=1,X3=2),COUNTIF($X$2:X3,1)+COUNTIF($X$2:X3,2),"")
A4: CAN-2026-00003 | B4: 46093 | C4: Amanda Anderson | D4: amanda.anderson@example.com | E4: Staff Accountant | F4: Finance | G4: Excel, Reconciliation, QuickBooks | H4: 10 | I4: 72000 | J4: Austin, TX | K4: 14 | L4: Staffing Agency | M4: Hired | N4: Not Currently Relevant | O4: Best overall fit | P4: Yes | Q4: Yes | U4: =IF(A4="","",IF(AND(R4<>"",R4<=TODAY()+30,P4="Yes",Q4="Yes",N4<>"Do Not Contact"),1,0)) -> 0 | V4: =IF(U4=1,COUNTIF($U$2:U4,1),"") | W4: =IF(A4="","",A4&" | "&C4) -> CAN-2026-00003 | Amanda Anderson | X4: =IF(A4="","",IF(AND(R4<>"",P4="Yes",Q4="Yes",N4<>"Do Not Contact"),IF(INT(R4)=TODAY(),1,IF(INT(R4)=TODAY()+1,2,0)),0)) -> 0 | Y4: =IF(OR(X4=1,X4=2),COUNTIF($X$2:X4,1)+COUNTIF($X$2:X4,2),"")
A5: CAN-2026-00004 | B5: 46099 | C5: Ashley Martinez | D5: ashley.martinez@example.com | E5: Quality Engineer | F5: Engineering | G5: ISO 9001, FMEA, Root Cause Analysis, Git, Process Improvement | H5: 2 | I5: 106000 | J5: Columbus, OH | K5: 14 | L5: LinkedIn | M5: Not Selected | N5: Strong Future Fit | O5: Skill gap in a key requirement | P5: Yes | Q5: Yes | R5: 46387 | S5: 46293 | T5: Interested | U5: =IF(A5="","",IF(AND(R5<>"",R5<=TODAY()+30,P5="Yes",Q5="Yes",N5<>"Do Not Contact"),1,0)) -> 0 | V5: =IF(U5=1,COUNTIF($U$2:U5,1),"") | W5: =IF(A5="","",A5&" | "&C5) -> CAN-2026-00004 | Ashley Martinez | X5: =IF(A5="","",IF(AND(R5<>"",P5="Yes",Q5="Yes",N5<>"Do Not Contact"),IF(INT(R5)=TODAY(),1,IF(INT(R5)=TODAY()+1,2,0)),0)) -> 0 | Y5: =IF(OR(X5=1,X5=2),COUNTIF($X$2:X5,1)+COUNTIF($X$2:X5,2),"")
A6: CAN-2026-00005 | B6: 46103 | C6: Joshua Martinez | D6: joshua.martinez@example.com | E6: Staff Accountant | F6: Finance | G6: QuickBooks, Excel, Accounts Payable, GAAP, Tableau | H6: 2 | I6: 79000 | J6: Denver, CO | K6: 14 | L6: Company Website | M6: Not Selected | N6: Potential Future Fit | O6: Salary expectation above budget | P6: Yes | Q6: Yes | R6: 46386 | S6: 46285 | T6: No response | U6: =IF(A6="","",IF(AND(R6<>"",R6<=TODAY()+30,P6="Yes",Q6="Yes",N6<>"Do Not Contact"),1,0)) -> 0 | V6: =IF(U6=1,COUNTIF($U$2:U6,1),"") | W6: =IF(A6="","",A6&" | "&C6) -> CAN-2026-00005 | Joshua Martinez | X6: =IF(A6="","",IF(AND(R6<>"",P6="Yes",Q6="Yes",N6<>"Do Not Contact"),IF(INT(R6)=TODAY(),1,IF(INT(R6)=TODAY()+1,2,0)),0)) -> 0 | Y6: =IF(OR(X6=1,X6=2),COUNTIF($X$2:X6,1)+COUNTIF($X$2:X6,2),"")
A7: CAN-2026-00006 | B7: 46107 | C7: Kevin Davis | D7: kevin.davis@example.com | E7: Operations Manager | F7: Operations | G7: Supply Chain, Team Leadership, Process Improvement, Budgeting | H7: 9 | I7: 103000 | J7: Chicago, IL | K7: 14 | L7: Company Website | M7: Not Selected | N7: Not Currently Relevant | O7: Skill gap in a key requirement | P7: Yes | Q7: No | U7: =IF(A7="","",IF(AND(R7<>"",R7<=TODAY()+30,P7="Yes",Q7="Yes",N7<>"Do Not Contact"),1,0)) -> 0 | V7: =IF(U7=1,COUNTIF($U$2:U7,1),"") | W7: =IF(A7="","",A7&" | "&C7) -> CAN-2026-00006 | Kevin Davis | X7: =IF(A7="","",IF(AND(R7<>"",P7="Yes",Q7="Yes",N7<>"Do Not Contact"),IF(INT(R7)=TODAY(),1,IF(INT(R7)=TODAY()+1,2,0)),0)) -> 0 | Y7: =IF(OR(X7=1,X7=2),COUNTIF($X$2:X7,1)+COUNTIF($X$2:X7,2),"")
A8: CAN-2026-00007 | B8: 46120 | C8: Nicole Brown | D8: nicole.brown@example.com | E8: Marketing Manager | F8: Marketing | G8: Google Analytics, SEO, Content Strategy, Email Marketing | H8: 5 | I8: 96000 | J8: Atlanta, GA | K8: 14 | L8: Referral | M8: Not Selected | N8: Strong Future Fit | O8: Insufficient experience for this level | P8: Yes | Q8: Yes | R8: 46311 | S8: 46289 | T8: Interested | U8: =IF(A8="","",IF(AND(R8<>"",R8<=TODAY()+30,P8="Yes",Q8="Yes",N8<>"Do Not Contact"),1,0)) -> 1 | V8: =IF(U8=1,COUNTIF($U$2:U8,1),"") -> 1 | W8: =IF(A8="","",A8&" | "&C8) -> CAN-2026-00007 | Nicole Brown | X8: =IF(A8="","",IF(AND(R8<>"",P8="Yes",Q8="Yes",N8<>"Do Not Contact"),IF(INT(R8)=TODAY(),1,IF(INT(R8)=TODAY()+1,2,0)),0)) -> 0 | Y8: =IF(OR(X8=1,X8=2),COUNTIF($X$2:X8,1)+COUNTIF($X$2:X8,2),"")
A9: CAN-2026-00008 | B9: 46121 | C9: Jessica Miller | D9: jessica.miller@example.com | E9: Quality Engineer | F9: Engineering | G9: ISO 9001, SPC, Internal Audit, Root Cause Analysis, FMEA, Email Marketing, B2B Sales | H9: 10 | I9: 86000 | J9: Atlanta, GA | K9: 60 | L9: Indeed | M9: Screened | N9: Potential Future Fit | O9: Passed CV screening | P9: Yes | Q9: Yes | R9: =TODAY() -> 46300 | U9: =IF(A9="","",IF(AND(R9<>"",R9<=TODAY()+30,P9="Yes",Q9="Yes",N9<>"Do Not Contact"),1,0)) -> 1 | V9: =IF(U9=1,COUNTIF($U$2:U9,1),"") -> 2 | W9: =IF(A9="","",A9&" | "&C9) -> CAN-2026-00008 | Jessica Miller | X9: =IF(A9="","",IF(AND(R9<>"",P9="Yes",Q9="Yes",N9<>"Do Not Contact"),IF(INT(R9)=TODAY(),1,IF(INT(R9)=TODAY()+1,2,0)),0)) -> 1 | Y9: =IF(OR(X9=1,X9=2),COUNTIF($X$2:X9,1)+COUNTIF($X$2:X9,2),"") -> 1
A10: CAN-2026-00009 | B10: 46128 | C10: Ashley Williams | D10: ashley.williams@example.com | E10: Marketing Manager | F10: Marketing | G10: Budgeting, Email Marketing, Google Analytics, SEO, CRM, Onboarding | H10: 10 | I10: 79000 | J10: Austin, TX | K10: 14 | L10: Indeed | M10: Withdrawn | N10: Not Currently Relevant | O10: Relocation not possible | P10: Yes | Q10: Yes | U10: =IF(A10="","",IF(AND(R10<>"",R10<=TODAY()+30,P10="Yes",Q10="Yes",N10<>"Do Not Contact"),1,0)) -> 0 | V10: =IF(U10=1,COUNTIF($U$2:U10,1),"") | W10: =IF(A10="","",A10&" | "&C10) -> CAN-2026-00009 | Ashley Williams | X10: =IF(A10="","",IF(AND(R10<>"",P10="Yes",Q10="Yes",N10<>"Do Not Contact"),IF(INT(R10)=TODAY(),1,IF(INT(R10)=TODAY()+1,2,0)),0)) -> 0 | Y10: =IF(OR(X10=1,X10=2),COUNTIF($X$2:X10,1)+COUNTIF($X$2:X10,2),"")
A11: CAN-2026-00010 | B11: 46132 | C11: Ashley Thompson | D11: ashley.thompson@example.com | E11: Marketing Manager | F11: Marketing | G11: Google Analytics, SEO, Content Strategy, Email Marketing, Root Cause Analysis | H11: 1 | I11: 114000 | J11: Atlanta, GA | K11: 30 | L11: Referral | M11: Screened | N11: Strong Future Fit | O11: Passed CV screening | P11: Yes | Q11: Yes | R11: 46371 | S11: 46285 | T11: Interested | U11: =IF(A11="","",IF(AND(R11<>"",R11<=TODAY()+30,P11="Yes",Q11="Yes",N11<>"Do Not Contact"),1,0)) -> 0 | V11: =IF(U11=1,COUNTIF($U$2:U11,1),"") | W11: =IF(A11="","",A11&" | "&C11) -> CAN-2026-00010 | Ashley Thompson | X11: =IF(A11="","",IF(AND(R11<>"",P11="Yes",Q11="Yes",N11<>"Do Not Contact"),IF(INT(R11)=TODAY(),1,IF(INT(R11)=TODAY()+1,2,0)),0)) -> 0 | Y11: =IF(OR(X11=1,X11=2),COUNTIF($X$2:X11,1)+COUNTIF($X$2:X11,2),"")
A12: CAN-2026-00011 | B12: 46137 | C12: Nicole Garcia | D12: nicole.garcia@example.com | E12: Account Executive | F12: Sales | G12: B2B Sales, Negotiation, Salesforce, CRM, Pipeline Management | H12: 5 | I12: 81000 | J12: Austin, TX | K12: 45 | L12: Company Website | M12: Interviewed | N12: Potential Future Fit | O12: Awaiting final decision | P12: Yes | Q12: Yes | R12: 46378 | U12: =IF(A12="","",IF(AND(R12<>"",R12<=TODAY()+30,P12="Yes",Q12="Yes",N12<>"Do Not Contact"),1,0)) -> 0 | V12: =IF(U12=1,COUNTIF($U$2:U12,1),"") | W12: =IF(A12="","",A12&" | "&C12) -> CAN-2026-00011 | Nicole Garcia | X12: =IF(A12="","",IF(AND(R12<>"",P12="Yes",Q12="Yes",N12<>"Do Not Contact"),IF(INT(R12)=TODAY(),1,IF(INT(R12)=TODAY()+1,2,0)),0)) -> 0 | Y12: =IF(OR(X12=1,X12=2),COUNTIF($X$2:X12,1)+COUNTIF($X$2:X12,2),"")
A13: CAN-2026-00012 | B13: 46137 | C13: Brittany Thomas | D13: brittany.thomas@example.com | E13: Account Executive | F13: Sales | G13: Pipeline Management, CRM, Salesforce, B2B Sales, Negotiation, FMEA | H13: 8 | I13: 87000 | J13: Dallas, TX | K13: 30 | L13: Company Website | M13: Interviewed | N13: Potential Future Fit | O13: Awaiting final decision | P13: Yes | Q13: Yes | R13: 46366 | U13: =IF(A13="","",IF(AND(R13<>"",R13<=TODAY()+30,P13="Yes",Q13="Yes",N13<>"Do Not Contact"),1,0)) -> 0 | V13: =IF(U13=1,COUNTIF($U$2:U13,1),"") | W13: =IF(A13="","",A13&" | "&C13) -> CAN-2026-00012 | Brittany Thomas | X13: =IF(A13="","",IF(AND(R13<>"",P13="Yes",Q13="Yes",N13<>"Do Not Contact"),IF(INT(R13)=TODAY(),1,IF(INT(R13)=TODAY()+1,2,0)),0)) -> 0 | Y13: =IF(OR(X13=1,X13=2),COUNTIF($X$2:X13,1)+COUNTIF($X$2:X13,2),"")
A14: CAN-2026-00013 | B14: 46139 | C14: Jessica Thomas | D14: jessica.thomas@example.com | E14: Marketing Manager | F14: Marketing | G14: Google Analytics, Content Strategy, Budgeting, Root Cause Analysis, Onboarding | H14: 10 | I14: 110000 | J14: Austin, TX | K14: 14 | L14: Company Website | M14: Not Selected | N14: Potential Future Fit | O14: Salary expectation above budget | P14: Yes | Q14: Yes | R14: =TODAY() -> 46300 | U14: =IF(A14="","",IF(AND(R14<>"",R14<=TODAY()+30,P14="Yes",Q14="Yes",N14<>"Do Not Contact"),1,0)) -> 1 | V14: =IF(U14=1,COUNTIF($U$2:U14,1),"") -> 3 | W14: =IF(A14="","",A14&" | "&C14) -> CAN-2026-00013 | Jessica Thomas | X14: =IF(A14="","",IF(AND(R14<>"",P14="Yes",Q14="Yes",N14<>"Do Not Contact"),IF(INT(R14)=TODAY(),1,IF(INT(R14)=TODAY()+1,2,0)),0)) -> 1 | Y14: =IF(OR(X14=1,X14=2),COUNTIF($X$2:X14,1)+COUNTIF($X$2:X14,2),"") -> 2
A15: CAN-2026-00014 | B15: 46143 | C15: Christopher Garcia | D15: christopher.garcia@example.com | E15: Operations Manager | F15: Operations | G15: Supply Chain, Team Leadership, Lean Six Sigma, Process Improvement | H15: 2 | I15: 125000 | J15: Atlanta, GA | K15: 0 | L15: Indeed | M15: Not Selected | N15: Do Not Contact | O15: Salary expectation above budget | P15: No | Q15: Yes | U15: =IF(A15="","",IF(AND(R15<>"",R15<=TODAY()+30,P15="Yes",Q15="Yes",N15<>"Do Not Contact"),1,0)) -> 0 | V15: =IF(U15=1,COUNTIF($U$2:U15,1),"") | W15: =IF(A15="","",A15&" | "&C15) -> CAN-2026-00014 | Christopher Garcia | X15: =IF(A15="","",IF(AND(R15<>"",P15="Yes",Q15="Yes",N15<>"Do Not Contact"),IF(INT(R15)=TODAY(),1,IF(INT(R15)=TODAY()+1,2,0)),0)) -> 0 | Y15: =IF(OR(X15=1,X15=2),COUNTIF($X$2:X15,1)+COUNTIF($X$2:X15,2),"")
A16: CAN-2026-00015 | B16: 46146 | C16: Jason Miller | D16: jason.miller@example.com | E16: Operations Manager | F16: Operations | G16: Process Improvement, Lean Six Sigma, Team Leadership | H16: 4 | I16: 96000 | J16: Austin, TX | K16: 30 | L16: Referral | M16: Hired | N16: Not Currently Relevant | O16: Best overall fit | P16: Yes | Q16: Yes | U16: =IF(A16="","",IF(AND(R16<>"",R16<=TODAY()+30,P16="Yes",Q16="Yes",N16<>"Do Not Contact"),1,0)) -> 0 | V16: =IF(U16=1,COUNTIF($U$2:U16,1),"") | W16: =IF(A16="","",A16&" | "&C16) -> CAN-2026-00015 | Jason Miller | X16: =IF(A16="","",IF(AND(R16<>"",P16="Yes",Q16="Yes",N16<>"Do Not Contact"),IF(INT(R16)=TODAY(),1,IF(INT(R16)=TODAY()+1,2,0)),0)) -> 0 | Y16: =IF(OR(X16=1,X16=2),COUNTIF($X$2:X16,1)+COUNTIF($X$2:X16,2),"")
A17: CAN-2026-00016 | B17: 46151 | C17: Brittany Jackson | D17: brittany.jackson@example.com | E17: Data Analyst | F17: Analytics | G17: Excel, SQL, Python, Employee Relations | H17: 3 | I17: 96000 | J17: Denver, CO | K17: 30 | L17: Company Website | M17: Withdrawn | N17: Strong Future Fit | O17: Accepted another offer | P17: No | Q17: Yes | U17: =IF(A17="","",IF(AND(R17<>"",R17<=TODAY()+30,P17="Yes",Q17="Yes",N17<>"Do Not Contact"),1,0)) -> 0 | V17: =IF(U17=1,COUNTIF($U$2:U17,1),"") | W17: =IF(A17="","",A17&" | "&C17) -> CAN-2026-00016 | Brittany Jackson | X17: =IF(A17="","",IF(AND(R17<>"",P17="Yes",Q17="Yes",N17<>"Do Not Contact"),IF(INT(R17)=TODAY(),1,IF(INT(R17)=TODAY()+1,2,0)),0)) -> 0 | Y17: =IF(OR(X17=1,X17=2),COUNTIF($X$2:X17,1)+COUNTIF($X$2:X17,2),"")
A18: CAN-2026-00017 | B18: 46155 | C18: Emily Martin | D18: emily.martin@example.com | E18: Staff Accountant | F18: Finance | G18: GAAP, Reconciliation, Accounts Payable, QuickBooks, Excel, SEO, CRM | H18: 8 | I18: 56000 | J18: Dallas, TX | K18: 14 | L18: Indeed | M18: Not Selected | N18: Do Not Contact | O18: Insufficient experience for this level | P18: No | Q18: Yes | U18: =IF(A18="","",IF(AND(R18<>"",R18<=TODAY()+30,P18="Yes",Q18="Yes",N18<>"Do Not Contact"),1,0)) -> 0 | V18: =IF(U18=1,COUNTIF($U$2:U18,1),"") | W18: =IF(A18="","",A18&" | "&C18) -> CAN-2026-00017 | Emily Martin | X18: =IF(A18="","",IF(AND(R18<>"",P18="Yes",Q18="Yes",N18<>"Do Not Contact"),IF(INT(R18)=TODAY(),1,IF(INT(R18)=TODAY()+1,2,0)),0)) -> 0 | Y18: =IF(OR(X18=1,X18=2),COUNTIF($X$2:X18,1)+COUNTIF($X$2:X18,2),"")
A19: CAN-2026-00018 | B19: 46175 | C19: Jessica Anderson | D19: jessica.anderson@example.com | E19: Quality Engineer | F19: Engineering | G19: Root Cause Analysis, FMEA, ISO 9001 | H19: 3 | I19: 81000 | J19: Austin, TX | K19: 60 | L19: Indeed | M19: Not Selected | N19: Potential Future Fit | O19: Stronger candidate selected | P19: Yes | Q19: Yes | R19: =TODAY()+1 -> 46301 | U19: =IF(A19="","",IF(AND(R19<>"",R19<=TODAY()+30,P19="Yes",Q19="Yes",N19<>"Do Not Contact"),1,0)) -> 1 | V19: =IF(U19=1,COUNTIF($U$2:U19,1),"") -> 4 | W19: =IF(A19="","",A19&" | "&C19) -> CAN-2026-00018 | Jessica Anderson | X19: =IF(A19="","",IF(AND(R19<>"",P19="Yes",Q19="Yes",N19<>"Do Not Contact"),IF(INT(R19)=TODAY(),1,IF(INT(R19)=TODAY()+1,2,0)),0)) -> 2 | Y19: =IF(OR(X19=1,X19=2),COUNTIF($X$2:X19,1)+COUNTIF($X$2:X19,2),"") -> 3
A20: CAN-2026-00019 | B20: 46179 | C20: Jessica Wilson | D20: jessica.wilson@example.com | E20: Software Engineer | F20: Engineering | G20: AWS, SQL, Python, JavaScript, Excel, Recruiting | H20: 4 | I20: 112000 | J20: Austin, TX | K20: 14 | L20: Indeed | M20: Not Selected | N20: Not Currently Relevant | O20: Salary expectation above budget | P20: Yes | Q20: Yes | U20: =IF(A20="","",IF(AND(R20<>"",R20<=TODAY()+30,P20="Yes",Q20="Yes",N20<>"Do Not Contact"),1,0)) -> 0 | V20: =IF(U20=1,COUNTIF($U$2:U20,1),"") | W20: =IF(A20="","",A20&" | "&C20) -> CAN-2026-00019 | Jessica Wilson | X20: =IF(A20="","",IF(AND(R20<>"",P20="Yes",Q20="Yes",N20<>"Do Not Contact"),IF(INT(R20)=TODAY(),1,IF(INT(R20)=TODAY()+1,2,0)),0)) -> 0 | Y20: =IF(OR(X20=1,X20=2),COUNTIF($X$2:X20,1)+COUNTIF($X$2:X20,2),"")
A21: CAN-2026-00020 | B21: 46182 | C21: Ashley Thomas | D21: ashley.thomas@example.com | E21: Marketing Manager | F21: Marketing | G21: Budgeting, Google Analytics, SEO, ISO 9001, FMEA | H21: 3 | I21: 79000 | J21: Columbus, OH | K21: 60 | L21: Company Website | M21: Withdrawn | N21: Potential Future Fit | O21: Relocation not possible | P21: Yes | Q21: Yes | R21: 46283 | U21: =IF(A21="","",IF(AND(R21<>"",R21<=TODAY()+30,P21="Yes",Q21="Yes",N21<>"Do Not Contact"),1,0)) -> 1 | V21: =IF(U21=1,COUNTIF($U$2:U21,1),"") -> 5 | W21: =IF(A21="","",A21&" | "&C21) -> CAN-2026-00020 | Ashley Thomas | X21: =IF(A21="","",IF(AND(R21<>"",P21="Yes",Q21="Yes",N21<>"Do Not Contact"),IF(INT(R21)=TODAY(),1,IF(INT(R21)=TODAY()+1,2,0)),0)) -> 0 | Y21: =IF(OR(X21=1,X21=2),COUNTIF($X$2:X21,1)+COUNTIF($X$2:X21,2),"")
A22: CAN-2026-00021 | B22: 46182 | C22: Tyler Jackson | D22: tyler.jackson@example.com | E22: Operations Manager | F22: Operations | G22: Process Improvement, Team Leadership, Budgeting, Tableau | H22: 9 | I22: 120000 | J22: Columbus, OH | K22: 14 | L22: LinkedIn | M22: Not Selected | N22: Strong Future Fit | O22: Salary expectation above budget | P22: Yes | Q22: No | R22: 46385 | U22: =IF(A22="","",IF(AND(R22<>"",R22<=TODAY()+30,P22="Yes",Q22="Yes",N22<>"Do Not Contact"),1,0)) -> 0 | V22: =IF(U22=1,COUNTIF($U$2:U22,1),"") | W22: =IF(A22="","",A22&" | "&C22) -> CAN-2026-00021 | Tyler Jackson | X22: =IF(A22="","",IF(AND(R22<>"",P22="Yes",Q22="Yes",N22<>"Do Not Contact"),IF(INT(R22)=TODAY(),1,IF(INT(R22)=TODAY()+1,2,0)),0)) -> 0 | Y22: =IF(OR(X22=1,X22=2),COUNTIF($X$2:X22,1)+COUNTIF($X$2:X22,2),"")
A23: CAN-2026-00022 | B23: 46194 | C23: Megan Martin | D23: megan.martin@example.com | E23: Quality Engineer | F23: Engineering | G23: ISO 9001, SPC, FMEA, Root Cause Analysis | H23: 3 | I23: 76000 | J23: Dallas, TX | K23: 0 | L23: LinkedIn | M23: Not Selected | N23: Potential Future Fit | O23: Stronger candidate selected | P23: Yes | Q23: Yes | R23: =TODAY()+1 -> 46301 | U23: =IF(A23="","",IF(AND(R23<>"",R23<=TODAY()+30,P23="Yes",Q23="Yes",N23<>"Do Not Contact"),1,0)) -> 1 | V23: =IF(U23=1,COUNTIF($U$2:U23,1),"") -> 6 | W23: =IF(A23="","",A23&" | "&C23) -> CAN-2026-00022 | Megan Martin | X23: =IF(A23="","",IF(AND(R23<>"",P23="Yes",Q23="Yes",N23<>"Do Not Contact"),IF(INT(R23)=TODAY(),1,IF(INT(R23)=TODAY()+1,2,0)),0)) -> 2 | Y23: =IF(OR(X23=1,X23=2),COUNTIF($X$2:X23,1)+COUNTIF($X$2:X23,2),"") -> 4
A24: CAN-2026-00023 | B24: 46196 | C24: Sarah Martinez | D24: sarah.martinez@example.com | E24: Marketing Manager | F24: Marketing | G24: SEO, Budgeting, Content Strategy, Google Analytics, Email Marketing | H24: 6 | I24: 116000 | J24: Atlanta, GA | K24: 14 | L24: Indeed | M24: Not Selected | N24: Not Currently Relevant | O24: Stronger candidate selected | P24: Yes | Q24: Yes | U24: =IF(A24="","",IF(AND(R24<>"",R24<=TODAY()+30,P24="Yes",Q24="Yes",N24<>"Do Not Contact"),1,0)) -> 0 | V24: =IF(U24=1,COUNTIF($U$2:U24,1),"") | W24: =IF(A24="","",A24&" | "&C24) -> CAN-2026-00023 | Sarah Martinez | X24: =IF(A24="","",IF(AND(R24<>"",P24="Yes",Q24="Yes",N24<>"Do Not Contact"),IF(INT(R24)=TODAY(),1,IF(INT(R24)=TODAY()+1,2,0)),0)) -> 0 | Y24: =IF(OR(X24=1,X24=2),COUNTIF($X$2:X24,1)+COUNTIF($X$2:X24,2),"")
A25: CAN-2026-00024 | B25: 46197 | C25: Lauren Davis | D25: lauren.davis@example.com | E25: Staff Accountant | F25: Finance | G25: GAAP, Excel, Reconciliation, QuickBooks, Benefits Administration | H25: 5 | I25: 65000 | J25: Austin, TX | K25: 14 | L25: Staffing Agency | M25: Not Selected | N25: Not Currently Relevant | O25: Stronger candidate selected | P25: Yes | Q25: Yes | U25: =IF(A25="","",IF(AND(R25<>"",R25<=TODAY()+30,P25="Yes",Q25="Yes",N25<>"Do Not Contact"),1,0)) -> 0 | V25: =IF(U25=1,COUNTIF($U$2:U25,1),"") | W25: =IF(A25="","",A25&" | "&C25) -> CAN-2026-00024 | Lauren Davis | X25: =IF(A25="","",IF(AND(R25<>"",P25="Yes",Q25="Yes",N25<>"Do Not Contact"),IF(INT(R25)=TODAY(),1,IF(INT(R25)=TODAY()+1,2,0)),0)) -> 0 | Y25: =IF(OR(X25=1,X25=2),COUNTIF($X$2:X25,1)+COUNTIF($X$2:X25,2),"")
A26: CAN-2026-00025 | B26: 46199 | C26: Amanda Thompson | D26: amanda.thompson@example.com | E26: HR Generalist | F26: Human Resources | G26: Recruiting, Onboarding, HRIS, GAAP, Python | H26: 3 | I26: 65000 | J26: Chicago, IL | K26: 30 | L26: Referral | M26: Not Selected | N26: Potential Future Fit | O26: Skill gap in a key requirement | P26: Yes | Q26: Yes | R26: 46303 | U26: =IF(A26="","",IF(AND(R26<>"",R26<=TODAY()+30,P26="Yes",Q26="Yes",N26<>"Do Not Contact"),1,0)) -> 1 | V26: =IF(U26=1,COUNTIF($U$2:U26,1),"") -> 7 | W26: =IF(A26="","",A26&" | "&C26) -> CAN-2026-00025 | Amanda Thompson | X26: =IF(A26="","",IF(AND(R26<>"",P26="Yes",Q26="Yes",N26<>"Do Not Contact"),IF(INT(R26)=TODAY(),1,IF(INT(R26)=TODAY()+1,2,0)),0)) -> 0 | Y26: =IF(OR(X26=1,X26=2),COUNTIF($X$2:X26,1)+COUNTIF($X$2:X26,2),"")
A27: CAN-2026-00026 | B27: 46203 | C27: Jason White | D27: jason.white@example.com | E27: Staff Accountant | F27: Finance | G27: Accounts Payable, QuickBooks, Excel | H27: 5 | I27: 68000 | J27: Austin, TX | K27: 14 | L27: Staffing Agency | M27: Not Selected | N27: Potential Future Fit | O27: Stronger candidate selected | P27: Yes | Q27: Yes | R27: =TODAY()+1 -> 46301 | U27: =IF(A27="","",IF(AND(R27<>"",R27<=TODAY()+30,P27="Yes",Q27="Yes",N27<>"Do Not Contact"),1,0)) -> 1 | V27: =IF(U27=1,COUNTIF($U$2:U27,1),"") -> 8 | W27: =IF(A27="","",A27&" | "&C27) -> CAN-2026-00026 | Jason White | X27: =IF(A27="","",IF(AND(R27<>"",P27="Yes",Q27="Yes",N27<>"Do Not Contact"),IF(INT(R27)=TODAY(),1,IF(INT(R27)=TODAY()+1,2,0)),0)) -> 2 | Y27: =IF(OR(X27=1,X27=2),COUNTIF($X$2:X27,1)+COUNTIF($X$2:X27,2),"") -> 5
A28: CAN-2026-00027 | B28: 46210 | C28: Amanda Thomas | D28: amanda.thomas@example.com | E28: Quality Engineer | F28: Engineering | G28: Root Cause Analysis, FMEA, Internal Audit, SPC, ISO 9001 | H28: 8 | I28: 92000 | J28: Columbus, OH | K28: 30 | L28: Company Website | M28: Interviewed | N28: Not Currently Relevant | O28: Awaiting final decision | P28: Yes | Q28: No | U28: =IF(A28="","",IF(AND(R28<>"",R28<=TODAY()+30,P28="Yes",Q28="Yes",N28<>"Do Not Contact"),1,0)) -> 0 | V28: =IF(U28=1,COUNTIF($U$2:U28,1),"") | W28: =IF(A28="","",A28&" | "&C28) -> CAN-2026-00027 | Amanda Thomas | X28: =IF(A28="","",IF(AND(R28<>"",P28="Yes",Q28="Yes",N28<>"Do Not Contact"),IF(INT(R28)=TODAY(),1,IF(INT(R28)=TODAY()+1,2,0)),0)) -> 0 | Y28: =IF(OR(X28=1,X28=2),COUNTIF($X$2:X28,1)+COUNTIF($X$2:X28,2),"")
A29: CAN-2026-00028 | B29: 46217 | C29: Daniel Brown | D29: daniel.brown@example.com | E29: HR Generalist | F29: Human Resources | G29: HRIS, Benefits Administration, Employee Relations, Content Strategy, Negotiation | H29: 6 | I29: 62000 | J29: Dallas, TX | K29: 0 | L29: Staffing Agency | M29: Withdrawn | N29: Not Currently Relevant | O29: Relocation not possible | P29: No | Q29: Yes | U29: =IF(A29="","",IF(AND(R29<>"",R29<=TODAY()+30,P29="Yes",Q29="Yes",N29<>"Do Not Contact"),1,0)) -> 0 | V29: =IF(U29=1,COUNTIF($U$2:U29,1),"") | W29: =IF(A29="","",A29&" | "&C29) -> CAN-2026-00028 | Daniel Brown | X29: =IF(A29="","",IF(AND(R29<>"",P29="Yes",Q29="Yes",N29<>"Do Not Contact"),IF(INT(R29)=TODAY(),1,IF(INT(R29)=TODAY()+1,2,0)),0)) -> 0 | Y29: =IF(OR(X29=1,X29=2),COUNTIF($X$2:X29,1)+COUNTIF($X$2:X29,2),"")
A30: CAN-2026-00029 | B30: 46219 | C30: Megan Garcia | D30: megan.garcia@example.com | E30: Operations Manager | F30: Operations | G30: Process Improvement, Lean Six Sigma, Team Leadership, Budgeting, Supply Chain, Root Cause Analysis | H30: 2 | I30: 112000 | J30: Chicago, IL | K30: 60 | L30: Referral | M30: Hired | N30: Not Currently Relevant | O30: Best overall fit | P30: No | Q30: Yes | U30: =IF(A30="","",IF(AND(R30<>"",R30<=TODAY()+30,P30="Yes",Q30="Yes",N30<>"Do Not Contact"),1,0)) -> 0 | V30: =IF(U30=1,COUNTIF($U$2:U30,1),"") | W30: =IF(A30="","",A30&" | "&C30) -> CAN-2026-00029 | Megan Garcia | X30: =IF(A30="","",IF(AND(R30<>"",P30="Yes",Q30="Yes",N30<>"Do Not Contact"),IF(INT(R30)=TODAY(),1,IF(INT(R30)=TODAY()+1,2,0)),0)) -> 0 | Y30: =IF(OR(X30=1,X30=2),COUNTIF($X$2:X30,1)+COUNTIF($X$2:X30,2),"")
A31: CAN-2026-00030 | B31: 46219 | C31: Christopher Davis | D31: christopher.davis@example.com | E31: Data Analyst | F31: Analytics | G31: Reporting, Excel, Python, Tableau | H31: 5 | I31: 102000 | J31: Atlanta, GA | K31: 30 | L31: Indeed | M31: Not Selected | N31: Not Currently Relevant | O31: Insufficient experience for this level | P31: Yes | Q31: No | U31: =IF(A31="","",IF(AND(R31<>"",R31<=TODAY()+30,P31="Yes",Q31="Yes",N31<>"Do Not Contact"),1,0)) -> 0 | V31: =IF(U31=1,COUNTIF($U$2:U31,1),"") | W31: =IF(A31="","",A31&" | "&C31) -> CAN-2026-00030 | Christopher Davis | X31: =IF(A31="","",IF(AND(R31<>"",P31="Yes",Q31="Yes",N31<>"Do Not Contact"),IF(INT(R31)=TODAY(),1,IF(INT(R31)=TODAY()+1,2,0)),0)) -> 0 | Y31: =IF(OR(X31=1,X31=2),COUNTIF($X$2:X31,1)+COUNTIF($X$2:X31,2),"")
A32: CAN-2026-00031 | B32: 46225 | C32: Kevin Taylor | D32: kevin.taylor@example.com | E32: Account Executive | F32: Sales | G32: Pipeline Management, B2B Sales, Negotiation, Salesforce, Lean Six Sigma, Supply Chain | H32: 8 | I32: 81000 | J32: Chicago, IL | K32: 45 | L32: Company Website | M32: Screened | N32: Strong Future Fit | O32: Passed CV screening | P32: Yes | Q32: Yes | R32: =TODAY()-2 -> 46298 | U32: =IF(A32="","",IF(AND(R32<>"",R32<=TODAY()+30,P32="Yes",Q32="Yes",N32<>"Do Not Contact"),1,0)) -> 1 | V32: =IF(U32=1,COUNTIF($U$2:U32,1),"") -> 9 | W32: =IF(A32="","",A32&" | "&C32) -> CAN-2026-00031 | Kevin Taylor | X32: =IF(A32="","",IF(AND(R32<>"",P32="Yes",Q32="Yes",N32<>"Do Not Contact"),IF(INT(R32)=TODAY(),1,IF(INT(R32)=TODAY()+1,2,0)),0)) -> 0 | Y32: =IF(OR(X32=1,X32=2),COUNTIF($X$2:X32,1)+COUNTIF($X$2:X32,2),"")
A33: CAN-2026-00032 | B33: 46227 | C33: Ashley Taylor | D33: ashley.taylor@example.com | E33: Staff Accountant | F33: Finance | G33: QuickBooks, Accounts Payable, Excel | H33: 4 | I33: 79000 | J33: Denver, CO | K33: 45 | L33: Company Website | M33: Hired | N33: Not Currently Relevant | O33: Best overall fit | P33: Yes | Q33: Yes | U33: =IF(A33="","",IF(AND(R33<>"",R33<=TODAY()+30,P33="Yes",Q33="Yes",N33<>"Do Not Contact"),1,0)) -> 0 | V33: =IF(U33=1,COUNTIF($U$2:U33,1),"") | W33: =IF(A33="","",A33&" | "&C33) -> CAN-2026-00032 | Ashley Taylor | X33: =IF(A33="","",IF(AND(R33<>"",P33="Yes",Q33="Yes",N33<>"Do Not Contact"),IF(INT(R33)=TODAY(),1,IF(INT(R33)=TODAY()+1,2,0)),0)) -> 0 | Y33: =IF(OR(X33=1,X33=2),COUNTIF($X$2:X33,1)+COUNTIF($X$2:X33,2),"")
A34: CAN-2026-00033 | B34: 46233 | C34: Tyler White | D34: tyler.white@example.com | E34: Data Analyst | F34: Analytics | G34: Python, Reporting, Excel, SQL, Tableau | H34: 8 | I34: 95000 | J34: Austin, TX | K34: 60 | L34: Referral | M34: Screened | N34: Not Currently Relevant | O34: Passed CV screening | P34: Yes | Q34: No | U34: =IF(A34="","",IF(AND(R34<>"",R34<=TODAY()+30,P34="Yes",Q34="Yes",N34<>"Do Not Contact"),1,0)) -> 0 | V34: =IF(U34=1,COUNTIF($U$2:U34,1),"") | W34: =IF(A34="","",A34&" | "&C34) -> CAN-2026-00033 | Tyler White | X34: =IF(A34="","",IF(AND(R34<>"",P34="Yes",Q34="Yes",N34<>"Do Not Contact"),IF(INT(R34)=TODAY(),1,IF(INT(R34)=TODAY()+1,2,0)),0)) -> 0 | Y34: =IF(OR(X34=1,X34=2),COUNTIF($X$2:X34,1)+COUNTIF($X$2:X34,2),"")
A35: CAN-2026-00034 | B35: 46236 | C35: Nicole Miller | D35: nicole.miller@example.com | E35: Data Analyst | F35: Analytics | G35: Reporting, SQL, Python, Tableau, Google Analytics, Budgeting | H35: 8 | I35: 72000 | J35: Columbus, OH | K35: 60 | L35: Company Website | M35: Not Selected | N35: Strong Future Fit | O35: Insufficient experience for this level | P35: Yes | Q35: Yes | R35: 46326 | U35: =IF(A35="","",IF(AND(R35<>"",R35<=TODAY()+30,P35="Yes",Q35="Yes",N35<>"Do Not Contact"),1,0)) -> 1 | V35: =IF(U35=1,COUNTIF($U$2:U35,1),"") -> 10 | W35: =IF(A35="","",A35&" | "&C35) -> CAN-2026-00034 | Nicole Miller | X35: =IF(A35="","",IF(AND(R35<>"",P35="Yes",Q35="Yes",N35<>"Do Not Contact"),IF(INT(R35)=TODAY(),1,IF(INT(R35)=TODAY()+1,2,0)),0)) -> 0 | Y35: =IF(OR(X35=1,X35=2),COUNTIF($X$2:X35,1)+COUNTIF($X$2:X35,2),"")
A36: CAN-2026-00035 | B36: 46243 | C36: Rachel Taylor | D36: rachel.taylor@example.com | E36: Quality Engineer | F36: Engineering | G36: FMEA, ISO 9001, Root Cause Analysis, Internal Audit, Team Leadership, Git | H36: 4 | I36: 75000 | J36: Austin, TX | K36: 45 | L36: Company Website | M36: Hired | N36: Not Currently Relevant | O36: Best overall fit | P36: No | Q36: Yes | U36: =IF(A36="","",IF(AND(R36<>"",R36<=TODAY()+30,P36="Yes",Q36="Yes",N36<>"Do Not Contact"),1,0)) -> 0 | V36: =IF(U36=1,COUNTIF($U$2:U36,1),"") | W36: =IF(A36="","",A36&" | "&C36) -> CAN-2026-00035 | Rachel Taylor | X36: =IF(A36="","",IF(AND(R36<>"",P36="Yes",Q36="Yes",N36<>"Do Not Contact"),IF(INT(R36)=TODAY(),1,IF(INT(R36)=TODAY()+1,2,0)),0)) -> 0 | Y36: =IF(OR(X36=1,X36=2),COUNTIF($X$2:X36,1)+COUNTIF($X$2:X36,2),"")
A37: CAN-2026-00036 | B37: 46244 | C37: Christopher Thompson | D37: christopher.thompson@example.com | E37: Software Engineer | F37: Engineering | G37: Git, SQL, AWS, Python, JavaScript, Email Marketing | H37: 7 | I37: 155000 | J37: Chicago, IL | K37: 14 | L37: LinkedIn | M37: Interviewed | N37: Potential Future Fit | O37: Awaiting final decision | P37: Yes | Q37: Yes | R37: 46297 | U37: =IF(A37="","",IF(AND(R37<>"",R37<=TODAY()+30,P37="Yes",Q37="Yes",N37<>"Do Not Contact"),1,0)) -> 1 | V37: =IF(U37=1,COUNTIF($U$2:U37,1),"") -> 11 | W37: =IF(A37="","",A37&" | "&C37) -> CAN-2026-00036 | Christopher Thompson | X37: =IF(A37="","",IF(AND(R37<>"",P37="Yes",Q37="Yes",N37<>"Do Not Contact"),IF(INT(R37)=TODAY(),1,IF(INT(R37)=TODAY()+1,2,0)),0)) -> 0 | Y37: =IF(OR(X37=1,X37=2),COUNTIF($X$2:X37,1)+COUNTIF($X$2:X37,2),"")
A38: CAN-2026-00037 | B38: 46247 | C38: Ashley Miller | D38: ashley.miller@example.com | E38: Data Analyst | F38: Analytics | G38: Python, SQL, Tableau, Reporting, Excel | H38: 5 | I38: 101000 | J38: Denver, CO | K38: 30 | L38: Staffing Agency | M38: Not Selected | N38: Potential Future Fit | O38: Insufficient experience for this level | P38: Yes | Q38: Yes | R38: =TODAY()+7 -> 46307 | U38: =IF(A38="","",IF(AND(R38<>"",R38<=TODAY()+30,P38="Yes",Q38="Yes",N38<>"Do Not Contact"),1,0)) -> 1 | V38: =IF(U38=1,COUNTIF($U$2:U38,1),"") -> 12 | W38: =IF(A38="","",A38&" | "&C38) -> CAN-2026-00037 | Ashley Miller | X38: =IF(A38="","",IF(AND(R38<>"",P38="Yes",Q38="Yes",N38<>"Do Not Contact"),IF(INT(R38)=TODAY(),1,IF(INT(R38)=TODAY()+1,2,0)),0)) -> 0 | Y38: =IF(OR(X38=1,X38=2),COUNTIF($X$2:X38,1)+COUNTIF($X$2:X38,2),"")
A39: CAN-2026-00038 | B39: 46258 | C39: Emily Martinez | D39: emily.martinez@example.com | E39: HR Generalist | F39: Human Resources | G39: HRIS, Recruiting, Onboarding, Employee Relations, Google Analytics, Python | H39: 9 | I39: 85000 | J39: Denver, CO | K39: 0 | L39: Company Website | M39: Not Selected | N39: Not Currently Relevant | O39: Timing: could not start soon enough | P39: Yes | Q39: Yes | U39: =IF(A39="","",IF(AND(R39<>"",R39<=TODAY()+30,P39="Yes",Q39="Yes",N39<>"Do Not Contact"),1,0)) -> 0 | V39: =IF(U39=1,COUNTIF($U$2:U39,1),"") | W39: =IF(A39="","",A39&" | "&C39) -> CAN-2026-00038 | Emily Martinez | X39: =IF(A39="","",IF(AND(R39<>"",P39="Yes",Q39="Yes",N39<>"Do Not Contact"),IF(INT(R39)=TODAY(),1,IF(INT(R39)=TODAY()+1,2,0)),0)) -> 0 | Y39: =IF(OR(X39=1,X39=2),COUNTIF($X$2:X39,1)+COUNTIF($X$2:X39,2),"")
A40: CAN-2026-00039 | B40: 46259 | C40: Kevin Miller | D40: kevin.miller@example.com | E40: Operations Manager | F40: Operations | G40: Supply Chain, Team Leadership, Budgeting, Process Improvement, Lean Six Sigma, Onboarding, Root Cause Analysis | H40: 4 | I40: 88000 | J40: Chicago, IL | K40: 14 | L40: Referral | M40: Not Selected | N40: Potential Future Fit | O40: Stronger candidate selected | P40: Yes | Q40: Yes | R40: 46362 | U40: =IF(A40="","",IF(AND(R40<>"",R40<=TODAY()+30,P40="Yes",Q40="Yes",N40<>"Do Not Contact"),1,0)) -> 0 | V40: =IF(U40=1,COUNTIF($U$2:U40,1),"") | W40: =IF(A40="","",A40&" | "&C40) -> CAN-2026-00039 | Kevin Miller | X40: =IF(A40="","",IF(AND(R40<>"",P40="Yes",Q40="Yes",N40<>"Do Not Contact"),IF(INT(R40)=TODAY(),1,IF(INT(R40)=TODAY()+1,2,0)),0)) -> 0 | Y40: =IF(OR(X40=1,X40=2),COUNTIF($X$2:X40,1)+COUNTIF($X$2:X40,2),"")
A41: CAN-2026-00040 | B41: 46266 | C41: Megan Martinez | D41: megan.martinez@example.com | E41: HR Generalist | F41: Human Resources | G41: Employee Relations, Benefits Administration, HRIS, Onboarding, Recruiting, Internal Audit | H41: 1 | I41: 67000 | J41: Columbus, OH | K41: 60 | L41: LinkedIn | M41: Not Selected | N41: Strong Future Fit | O41: Insufficient experience for this level | P41: Yes | Q41: Yes | R41: 46326 | U41: =IF(A41="","",IF(AND(R41<>"",R41<=TODAY()+30,P41="Yes",Q41="Yes",N41<>"Do Not Contact"),1,0)) -> 1 | V41: =IF(U41=1,COUNTIF($U$2:U41,1),"") -> 13 | W41: =IF(A41="","",A41&" | "&C41) -> CAN-2026-00040 | Megan Martinez | X41: =IF(A41="","",IF(AND(R41<>"",P41="Yes",Q41="Yes",N41<>"Do Not Contact"),IF(INT(R41)=TODAY(),1,IF(INT(R41)=TODAY()+1,2,0)),0)) -> 0 | Y41: =IF(OR(X41=1,X41=2),COUNTIF($X$2:X41,1)+COUNTIF($X$2:X41,2),"")
U42: =IF(A42="","",IF(AND(R42<>"",R42<=TODAY()+30,P42="Yes",Q42="Yes",N42<>"Do Not Contact"),1,0)) | V42: =IF(U42=1,COUNTIF($U$2:U42,1),"") | W42: =IF(A42="","",A42&" | "&C42) | X42: =IF(A42="","",IF(AND(R42<>"",P42="Yes",Q42="Yes",N42<>"Do Not Contact"),IF(INT(R42)=TODAY(),1,IF(INT(R42)=TODAY()+1,2,0)),0)) | Y42: =IF(OR(X42=1,X42=2),COUNTIF($X$2:X42,1)+COUNTIF($X$2:X42,2),"")
U43: =IF(A43="","",IF(AND(R43<>"",R43<=TODAY()+30,P43="Yes",Q43="Yes",N43<>"Do Not Contact"),1,0)) | V43: =IF(U43=1,COUNTIF($U$2:U43,1),"") | W43: =IF(A43="","",A43&" | "&C43) | X43: =IF(A43="","",IF(AND(R43<>"",P43="Yes",Q43="Yes",N43<>"Do Not Contact"),IF(INT(R43)=TODAY(),1,IF(INT(R43)=TODAY()+1,2,0)),0)) | Y43: =IF(OR(X43=1,X43=2),COUNTIF($X$2:X43,1)+COUNTIF($X$2:X43,2),"")
U44: =IF(A44="","",IF(AND(R44<>"",R44<=TODAY()+30,P44="Yes",Q44="Yes",N44<>"Do Not Contact"),1,0)) | V44: =IF(U44=1,COUNTIF($U$2:U44,1),"") | W44: =IF(A44="","",A44&" | "&C44) | X44: =IF(A44="","",IF(AND(R44<>"",P44="Yes",Q44="Yes",N44<>"Do Not Contact"),IF(INT(R44)=TODAY(),1,IF(INT(R44)=TODAY()+1,2,0)),0)) | Y44: =IF(OR(X44=1,X44=2),COUNTIF($X$2:X44,1)+COUNTIF($X$2:X44,2),"")
U45: =IF(A45="","",IF(AND(R45<>"",R45<=TODAY()+30,P45="Yes",Q45="Yes",N45<>"Do Not Contact"),1,0)) | V45: =IF(U45=1,COUNTIF($U$2:U45,1),"") | W45: =IF(A45="","",A45&" | "&C45) | X45: =IF(A45="","",IF(AND(R45<>"",P45="Yes",Q45="Yes",N45<>"Do Not Contact"),IF(INT(R45)=TODAY(),1,IF(INT(R45)=TODAY()+1,2,0)),0)) | Y45: =IF(OR(X45=1,X45=2),COUNTIF($X$2:X45,1)+COUNTIF($X$2:X45,2),"")
U46: =IF(A46="","",IF(AND(R46<>"",R46<=TODAY()+30,P46="Yes",Q46="Yes",N46<>"Do Not Contact"),1,0)) | V46: =IF(U46=1,COUNTIF($U$2:U46,1),"") | W46: =IF(A46="","",A46&" | "&C46) | X46: =IF(A46="","",IF(AND(R46<>"",P46="Yes",Q46="Yes",N46<>"Do Not Contact"),IF(INT(R46)=TODAY(),1,IF(INT(R46)=TODAY()+1,2,0)),0)) | Y46: =IF(OR(X46=1,X46=2),COUNTIF($X$2:X46,1)+COUNTIF($X$2:X46,2),"")
U47: =IF(A47="","",IF(AND(R47<>"",R47<=TODAY()+30,P47="Yes",Q47="Yes",N47<>"Do Not Contact"),1,0)) | V47: =IF(U47=1,COUNTIF($U$2:U47,1),"") | W47: =IF(A47="","",A47&" | "&C47) | X47: =IF(A47="","",IF(AND(R47<>"",P47="Yes",Q47="Yes",N47<>"Do Not Contact"),IF(INT(R47)=TODAY(),1,IF(INT(R47)=TODAY()+1,2,0)),0)) | Y47: =IF(OR(X47=1,X47=2),COUNTIF($X$2:X47,1)+COUNTIF($X$2:X47,2),"")
U48: =IF(A48="","",IF(AND(R48<>"",R48<=TODAY()+30,P48="Yes",Q48="Yes",N48<>"Do Not Contact"),1,0)) | V48: =IF(U48=1,COUNTIF($U$2:U48,1),"") | W48: =IF(A48="","",A48&" | "&C48) | X48: =IF(A48="","",IF(AND(R48<>"",P48="Yes",Q48="Yes",N48<>"Do Not Contact"),IF(INT(R48)=TODAY(),1,IF(INT(R48)=TODAY()+1,2,0)),0)) | Y48: =IF(OR(X48=1,X48=2),COUNTIF($X$2:X48,1)+COUNTIF($X$2:X48,2),"")
U49: =IF(A49="","",IF(AND(R49<>"",R49<=TODAY()+30,P49="Yes",Q49="Yes",N49<>"Do Not Contact"),1,0)) | V49: =IF(U49=1,COUNTIF($U$2:U49,1),"") | W49: =IF(A49="","",A49&" | "&C49) | X49: =IF(A49="","",IF(AND(R49<>"",P49="Yes",Q49="Yes",N49<>"Do Not Contact"),IF(INT(R49)=TODAY(),1,IF(INT(R49)=TODAY()+1,2,0)),0)) | Y49: =IF(OR(X49=1,X49=2),COUNTIF($X$2:X49,1)+COUNTIF($X$2:X49,2),"")
U50: =IF(A50="","",IF(AND(R50<>"",R50<=TODAY()+30,P50="Yes",Q50="Yes",N50<>"Do Not Contact"),1,0)) | V50: =IF(U50=1,COUNTIF($U$2:U50,1),"") | W50: =IF(A50="","",A50&" | "&C50) | X50: =IF(A50="","",IF(AND(R50<>"",P50="Yes",Q50="Yes",N50<>"Do Not Contact"),IF(INT(R50)=TODAY(),1,IF(INT(R50)=TODAY()+1,2,0)),0)) | Y50: =IF(OR(X50=1,X50=2),COUNTIF($X$2:X50,1)+COUNTIF($X$2:X50,2),"")
U51: =IF(A51="","",IF(AND(R51<>"",R51<=TODAY()+30,P51="Yes",Q51="Yes",N51<>"Do Not Contact"),1,0)) | V51: =IF(U51=1,COUNTIF($U$2:U51,1),"") | W51: =IF(A51="","",A51&" | "&C51) | X51: =IF(A51="","",IF(AND(R51<>"",P51="Yes",Q51="Yes",N51<>"Do Not Contact"),IF(INT(R51)=TODAY(),1,IF(INT(R51)=TODAY()+1,2,0)),0)) | Y51: =IF(OR(X51=1,X51=2),COUNTIF($X$2:X51,1)+COUNTIF($X$2:X51,2),"")
U52: =IF(A52="","",IF(AND(R52<>"",R52<=TODAY()+30,P52="Yes",Q52="Yes",N52<>"Do Not Contact"),1,0)) | V52: =IF(U52=1,COUNTIF($U$2:U52,1),"") | W52: =IF(A52="","",A52&" | "&C52) | X52: =IF(A52="","",IF(AND(R52<>"",P52="Yes",Q52="Yes",N52<>"Do Not Contact"),IF(INT(R52)=TODAY(),1,IF(INT(R52)=TODAY()+1,2,0)),0)) | Y52: =IF(OR(X52=1,X52=2),COUNTIF($X$2:X52,1)+COUNTIF($X$2:X52,2),"")
U53: =IF(A53="","",IF(AND(R53<>"",R53<=TODAY()+30,P53="Yes",Q53="Yes",N53<>"Do Not Contact"),1,0)) | V53: =IF(U53=1,COUNTIF($U$2:U53,1),"") | W53: =IF(A53="","",A53&" | "&C53) | X53: =IF(A53="","",IF(AND(R53<>"",P53="Yes",Q53="Yes",N53<>"Do Not Contact"),IF(INT(R53)=TODAY(),1,IF(INT(R53)=TODAY()+1,2,0)),0)) | Y53: =IF(OR(X53=1,X53=2),COUNTIF($X$2:X53,1)+COUNTIF($X$2:X53,2),"")
... U201: =IF(A201="","",IF(AND(R201<>"",R201<=TODAY()+30,P201="Yes",Q201="Yes",N201<>"Do Not Contact"),1,0)) | V201: =IF(U201=1,COUNTIF($U$2:U201,1),"") | W201: =IF(A201="","",A201&" | "&C201) | X201: =IF(A201="","",IF(AND(R201<>"",P201="Yes",Q201="Yes",N201<>"Do Not Contact"),IF(INT(R201)=TODAY(),1,IF(INT(R201)=TODAY()+1,2,0)),0)) | Y201: =IF(OR(X201=1,X201=2),COUNTIF($X$2:X201,1)+COUNTIF($X$2:X201,2),"")

Sheet Follow-Up
A1: Follow-Up
A2: 🔒 PREMIUM FEATURE · Visible in the demo, locked until you get full access. Message the creator (Start Here tab) to unlock it.
A4: 📝 A. Log a follow-up | E4: What each outcome does
A5: 1. Choose the candidate | C5: Pick from the list (ID | name) | E5: Interested: stays in the pool, next follow-up date is updated.
A6: Candidate (automatic) | B6: =IFERROR(INDEX(Candidates!$C$2:$C$201,MATCH(LEFT(B5,FIND(" | ",B5&" | ")-1),Candidates!$A$2:$A$201,0))&" - last applied: "&INDEX(Candidates!$E$2:$E$201,MATCH(LEFT(B5,FIND(" | ",B5&" | ")-1),Candidates!$A$2:$A$201,0)),"") | C6: Check that this is the right person | E6: No response: stays in the pool, set a new follow-up date.
A7: 2. Date you contacted them | C7: e.g. 10/05/2026 (MM/DD/YYYY) | E7: Hired elsewhere: follow-up is cleared unless you enter a new date.
A8: 3. Outcome | C8: What was the result? | E8: Not interested: marked 'Interested in future roles = No' and removed from follow-up.
A9: 4. Notes (optional) | C9: Short note | E9: Do not contact again: marked Do Not Contact and excluded from all matching.
A10: 5. Next follow-up date (optional) | C10: Leave empty if no more follow-up is needed
A11: Then click SAVE FOLLOW-UP (or menu Talent Pool > Save follow-up).
A13: ⏰ B. Due now (next 30 days, including overdue)
A14: ="Total due: "&COUNTIF(Candidates!$U$2:$U$201,1) -> Total due: 13
A15: Candidate ID | B15: Name | C15: Contact | D15: Last position applied | E15: Future potential | F15: Next follow-up | G15: Status | H15: Last contact | I15: Last outcome
A16: =IFERROR(INDEX(Candidates!$A$2:$A$201,MATCH(1,Candidates!$V$2:$V$201,0))&"","") -> CAN-2026-00007 | B16: =IFERROR(INDEX(Candidates!$C$2:$C$201,MATCH(1,Candidates!$V$2:$V$201,0))&"","") -> Nicole Brown | C16: =IFERROR(INDEX(Candidates!$D$2:$D$201,MATCH(1,Candidates!$V$2:$V$201,0))&"","") -> nicole.brown@example.com | D16: =IFERROR(INDEX(Candidates!$E$2:$E$201,MATCH(1,Candidates!$V$2:$V$201,0))&"","") -> Marketing Manager | E16: =IFERROR(INDEX(Candidates!$N$2:$N$201,MATCH(1,Candidates!$V$2:$V$201,0))&"","") -> Strong Future Fit | F16: =IFERROR(IF(INDEX(Candidates!$R$2:$R$201,MATCH(1,Candidates!$V$2:$V$201,0))="","",INDEX(Candidates!$R$2:$R$201,MATCH(1,Candidates!$V$2:$V$201,0))),"") -> 46311 | G16: =IF(F16="","",IF(F16<TODAY(),"Overdue by "&(TODAY()-F16)&" days",IF(F16=TODAY(),"Due today","Due in "&(F16-TODAY())&" days"))) -> Due in 11 days | H16: =IFERROR(IF(INDEX(Candidates!$S$2:$S$201,MATCH(1,Candidates!$V$2:$V$201,0))="","",INDEX(Candidates!$S$2:$S$201,MATCH(1,Candidates!$V$2:$V$201,0))),"") -> 46289 | I16: =IFERROR(INDEX(Candidates!$T$2:$T$201,MATCH(1,Candidates!$V$2:$V$201,0))&"","") -> Interested
A17: =IFERROR(INDEX(Candidates!$A$2:$A$201,MATCH(2,Candidates!$V$2:$V$201,0))&"","") -> CAN-2026-00008 | B17: =IFERROR(INDEX(Candidates!$C$2:$C$201,MATCH(2,Candidates!$V$2:$V$201,0))&"","") -> Jessica Miller | C17: =IFERROR(INDEX(Candidates!$D$2:$D$201,MATCH(2,Candidates!$V$2:$V$201,0))&"","") -> jessica.miller@example.com | D17: =IFERROR(INDEX(Candidates!$E$2:$E$201,MATCH(2,Candidates!$V$2:$V$201,0))&"","") -> Quality Engineer | E17: =IFERROR(INDEX(Candidates!$N$2:$N$201,MATCH(2,Candidates!$V$2:$V$201,0))&"","") -> Potential Future Fit | F17: =IFERROR(IF(INDEX(Candidates!$R$2:$R$201,MATCH(2,Candidates!$V$2:$V$201,0))="","",INDEX(Candidates!$R$2:$R$201,MATCH(2,Candidates!$V$2:$V$201,0))),"") -> 46300 | G17: =IF(F17="","",IF(F17<TODAY(),"Overdue by "&(TODAY()-F17)&" days",IF(F17=TODAY(),"Due today","Due in "&(F17-TODAY())&" days"))) -> Due today | H17: =IFERROR(IF(INDEX(Candidates!$S$2:$S$201,MATCH(2,Candidates!$V$2:$V$201,0))="","",INDEX(Candidates!$S$2:$S$201,MATCH(2,Candidates!$V$2:$V$201,0))),"") | I17: =IFERROR(INDEX(Candidates!$T$2:$T$201,MATCH(2,Candidates!$V$2:$V$201,0))&"","")
A18: =IFERROR(INDEX(Candidates!$A$2:$A$201,MATCH(3,Candidates!$V$2:$V$201,0))&"","") -> CAN-2026-00013 | B18: =IFERROR(INDEX(Candidates!$C$2:$C$201,MATCH(3,Candidates!$V$2:$V$201,0))&"","") -> Jessica Thomas | C18: =IFERROR(INDEX(Candidates!$D$2:$D$201,MATCH(3,Candidates!$V$2:$V$201,0))&"","") -> jessica.thomas@example.com | D18: =IFERROR(INDEX(Candidates!$E$2:$E$201,MATCH(3,Candidates!$V$2:$V$201,0))&"","") -> Marketing Manager | E18: =IFERROR(INDEX(Candidates!$N$2:$N$201,MATCH(3,Candidates!$V$2:$V$201,0))&"","") -> Potential Future Fit | F18: =IFERROR(IF(INDEX(Candidates!$R$2:$R$201,MATCH(3,Candidates!$V$2:$V$201,0))="","",INDEX(Candidates!$R$2:$R$201,MATCH(3,Candidates!$V$2:$V$201,0))),"") -> 46300 | G18: =IF(F18="","",IF(F18<TODAY(),"Overdue by "&(TODAY()-F18)&" days",IF(F18=TODAY(),"Due today","Due in "&(F18-TODAY())&" days"))) -> Due today | H18: =IFERROR(IF(INDEX(Candidates!$S$2:$S$201,MATCH(3,Candidates!$V$2:$V$201,0))="","",INDEX(Candidates!$S$2:$S$201,MATCH(3,Candidates!$V$2:$V$201,0))),"") | I18: =IFERROR(INDEX(Candidates!$T$2:$T$201,MATCH(3,Candidates!$V$2:$V$201,0))&"","")
A19: =IFERROR(INDEX(Candidates!$A$2:$A$201,MATCH(4,Candidates!$V$2:$V$201,0))&"","") -> CAN-2026-00018 | B19: =IFERROR(INDEX(Candidates!$C$2:$C$201,MATCH(4,Candidates!$V$2:$V$201,0))&"","") -> Jessica Anderson | C19: =IFERROR(INDEX(Candidates!$D$2:$D$201,MATCH(4,Candidates!$V$2:$V$201,0))&"","") -> jessica.anderson@example.com | D19: =IFERROR(INDEX(Candidates!$E$2:$E$201,MATCH(4,Candidates!$V$2:$V$201,0))&"","") -> Quality Engineer | E19: =IFERROR(INDEX(Candidates!$N$2:$N$201,MATCH(4,Candidates!$V$2:$V$201,0))&"","") -> Potential Future Fit | F19: =IFERROR(IF(INDEX(Candidates!$R$2:$R$201,MATCH(4,Candidates!$V$2:$V$201,0))="","",INDEX(Candidates!$R$2:$R$201,MATCH(4,Candidates!$V$2:$V$201,0))),"") -> 46301 | G19: =IF(F19="","",IF(F19<TODAY(),"Overdue by "&(TODAY()-F19)&" days",IF(F19=TODAY(),"Due today","Due in "&(F19-TODAY())&" days"))) -> Due in 1 days | H19: =IFERROR(IF(INDEX(Candidates!$S$2:$S$201,MATCH(4,Candidates!$V$2:$V$201,0))="","",INDEX(Candidates!$S$2:$S$201,MATCH(4,Candidates!$V$2:$V$201,0))),"") | I19: =IFERROR(INDEX(Candidates!$T$2:$T$201,MATCH(4,Candidates!$V$2:$V$201,0))&"","")
A20: =IFERROR(INDEX(Candidates!$A$2:$A$201,MATCH(5,Candidates!$V$2:$V$201,0))&"","") -> CAN-2026-00020 | B20: =IFERROR(INDEX(Candidates!$C$2:$C$201,MATCH(5,Candidates!$V$2:$V$201,0))&"","") -> Ashley Thomas | C20: =IFERROR(INDEX(Candidates!$D$2:$D$201,MATCH(5,Candidates!$V$2:$V$201,0))&"","") -> ashley.thomas@example.com | D20: =IFERROR(INDEX(Candidates!$E$2:$E$201,MATCH(5,Candidates!$V$2:$V$201,0))&"","") -> Marketing Manager | E20: =IFERROR(INDEX(Candidates!$N$2:$N$201,MATCH(5,Candidates!$V$2:$V$201,0))&"","") -> Potential Future Fit | F20: =IFERROR(IF(INDEX(Candidates!$R$2:$R$201,MATCH(5,Candidates!$V$2:$V$201,0))="","",INDEX(Candidates!$R$2:$R$201,MATCH(5,Candidates!$V$2:$V$201,0))),"") -> 46283 | G20: =IF(F20="","",IF(F20<TODAY(),"Overdue by "&(TODAY()-F20)&" days",IF(F20=TODAY(),"Due today","Due in "&(F20-TODAY())&" days"))) -> Overdue by 17 days | H20: =IFERROR(IF(INDEX(Candidates!$S$2:$S$201,MATCH(5,Candidates!$V$2:$V$201,0))="","",INDEX(Candidates!$S$2:$S$201,MATCH(5,Candidates!$V$2:$V$201,0))),"") | I20: =IFERROR(INDEX(Candidates!$T$2:$T$201,MATCH(5,Candidates!$V$2:$V$201,0))&"","")
A21: =IFERROR(INDEX(Candidates!$A$2:$A$201,MATCH(6,Candidates!$V$2:$V$201,0))&"","") -> CAN-2026-00022 | B21: =IFERROR(INDEX(Candidates!$C$2:$C$201,MATCH(6,Candidates!$V$2:$V$201,0))&"","") -> Megan Martin | C21: =IFERROR(INDEX(Candidates!$D$2:$D$201,MATCH(6,Candidates!$V$2:$V$201,0))&"","") -> megan.martin@example.com | D21: =IFERROR(INDEX(Candidates!$E$2:$E$201,MATCH(6,Candidates!$V$2:$V$201,0))&"","") -> Quality Engineer | E21: =IFERROR(INDEX(Candidates!$N$2:$N$201,MATCH(6,Candidates!$V$2:$V$201,0))&"","") -> Potential Future Fit | F21: =IFERROR(IF(INDEX(Candidates!$R$2:$R$201,MATCH(6,Candidates!$V$2:$V$201,0))="","",INDEX(Candidates!$R$2:$R$201,MATCH(6,Candidates!$V$2:$V$201,0))),"") -> 46301 | G21: =IF(F21="","",IF(F21<TODAY(),"Overdue by "&(TODAY()-F21)&" days",IF(F21=TODAY(),"Due today","Due in "&(F21-TODAY())&" days"))) -> Due in 1 days | H21: =IFERROR(IF(INDEX(Candidates!$S$2:$S$201,MATCH(6,Candidates!$V$2:$V$201,0))="","",INDEX(Candidates!$S$2:$S$201,MATCH(6,Candidates!$V$2:$V$201,0))),"") | I21: =IFERROR(INDEX(Candidates!$T$2:$T$201,MATCH(6,Candidates!$V$2:$V$201,0))&"","")
A22: =IFERROR(INDEX(Candidates!$A$2:$A$201,MATCH(7,Candidates!$V$2:$V$201,0))&"","") -> CAN-2026-00025 | B22: =IFERROR(INDEX(Candidates!$C$2:$C$201,MATCH(7,Candidates!$V$2:$V$201,0))&"","") -> Amanda Thompson | C22: =IFERROR(INDEX(Candidates!$D$2:$D$201,MATCH(7,Candidates!$V$2:$V$201,0))&"","") -> amanda.thompson@example.com | D22: =IFERROR(INDEX(Candidates!$E$2:$E$201,MATCH(7,Candidates!$V$2:$V$201,0))&"","") -> HR Generalist | E22: =IFERROR(INDEX(Candidates!$N$2:$N$201,MATCH(7,Candidates!$V$2:$V$201,0))&"","") -> Potential Future Fit | F22: =IFERROR(IF(INDEX(Candidates!$R$2:$R$201,MATCH(7,Candidates!$V$2:$V$201,0))="","",INDEX(Candidates!$R$2:$R$201,MATCH(7,Candidates!$V$2:$V$201,0))),"") -> 46303 | G22: =IF(F22="","",IF(F22<TODAY(),"Overdue by "&(TODAY()-F22)&" days",IF(F22=TODAY(),"Due today","Due in "&(F22-TODAY())&" days"))) -> Due in 3 days | H22: =IFERROR(IF(INDEX(Candidates!$S$2:$S$201,MATCH(7,Candidates!$V$2:$V$201,0))="","",INDEX(Candidates!$S$2:$S$201,MATCH(7,Candidates!$V$2:$V$201,0))),"") | I22: =IFERROR(INDEX(Candidates!$T$2:$T$201,MATCH(7,Candidates!$V$2:$V$201,0))&"","")
A23: =IFERROR(INDEX(Candidates!$A$2:$A$201,MATCH(8,Candidates!$V$2:$V$201,0))&"","") -> CAN-2026-00026 | B23: =IFERROR(INDEX(Candidates!$C$2:$C$201,MATCH(8,Candidates!$V$2:$V$201,0))&"","") -> Jason White | C23: =IFERROR(INDEX(Candidates!$D$2:$D$201,MATCH(8,Candidates!$V$2:$V$201,0))&"","") -> jason.white@example.com | D23: =IFERROR(INDEX(Candidates!$E$2:$E$201,MATCH(8,Candidates!$V$2:$V$201,0))&"","") -> Staff Accountant | E23: =IFERROR(INDEX(Candidates!$N$2:$N$201,MATCH(8,Candidates!$V$2:$V$201,0))&"","") -> Potential Future Fit | F23: =IFERROR(IF(INDEX(Candidates!$R$2:$R$201,MATCH(8,Candidates!$V$2:$V$201,0))="","",INDEX(Candidates!$R$2:$R$201,MATCH(8,Candidates!$V$2:$V$201,0))),"") -> 46301 | G23: =IF(F23="","",IF(F23<TODAY(),"Overdue by "&(TODAY()-F23)&" days",IF(F23=TODAY(),"Due today","Due in "&(F23-TODAY())&" days"))) -> Due in 1 days | H23: =IFERROR(IF(INDEX(Candidates!$S$2:$S$201,MATCH(8,Candidates!$V$2:$V$201,0))="","",INDEX(Candidates!$S$2:$S$201,MATCH(8,Candidates!$V$2:$V$201,0))),"") | I23: =IFERROR(INDEX(Candidates!$T$2:$T$201,MATCH(8,Candidates!$V$2:$V$201,0))&"","")
A24: =IFERROR(INDEX(Candidates!$A$2:$A$201,MATCH(9,Candidates!$V$2:$V$201,0))&"","") -> CAN-2026-00031 | B24: =IFERROR(INDEX(Candidates!$C$2:$C$201,MATCH(9,Candidates!$V$2:$V$201,0))&"","") -> Kevin Taylor | C24: =IFERROR(INDEX(Candidates!$D$2:$D$201,MATCH(9,Candidates!$V$2:$V$201,0))&"","") -> kevin.taylor@example.com | D24: =IFERROR(INDEX(Candidates!$E$2:$E$201,MATCH(9,Candidates!$V$2:$V$201,0))&"","") -> Account Executive | E24: =IFERROR(INDEX(Candidates!$N$2:$N$201,MATCH(9,Candidates!$V$2:$V$201,0))&"","") -> Strong Future Fit | F24: =IFERROR(IF(INDEX(Candidates!$R$2:$R$201,MATCH(9,Candidates!$V$2:$V$201,0))="","",INDEX(Candidates!$R$2:$R$201,MATCH(9,Candidates!$V$2:$V$201,0))),"") -> 46298 | G24: =IF(F24="","",IF(F24<TODAY(),"Overdue by "&(TODAY()-F24)&" days",IF(F24=TODAY(),"Due today","Due in "&(F24-TODAY())&" days"))) -> Overdue by 2 days | H24: =IFERROR(IF(INDEX(Candidates!$S$2:$S$201,MATCH(9,Candidates!$V$2:$V$201,0))="","",INDEX(Candidates!$S$2:$S$201,MATCH(9,Candidates!$V$2:$V$201,0))),"") | I24: =IFERROR(INDEX(Candidates!$T$2:$T$201,MATCH(9,Candidates!$V$2:$V$201,0))&"","")
A25: =IFERROR(INDEX(Candidates!$A$2:$A$201,MATCH(10,Candidates!$V$2:$V$201,0))&"","") -> CAN-2026-00034 | B25: =IFERROR(INDEX(Candidates!$C$2:$C$201,MATCH(10,Candidates!$V$2:$V$201,0))&"","") -> Nicole Miller | C25: =IFERROR(INDEX(Candidates!$D$2:$D$201,MATCH(10,Candidates!$V$2:$V$201,0))&"","") -> nicole.miller@example.com | D25: =IFERROR(INDEX(Candidates!$E$2:$E$201,MATCH(10,Candidates!$V$2:$V$201,0))&"","") -> Data Analyst | E25: =IFERROR(INDEX(Candidates!$N$2:$N$201,MATCH(10,Candidates!$V$2:$V$201,0))&"","") -> Strong Future Fit | F25: =IFERROR(IF(INDEX(Candidates!$R$2:$R$201,MATCH(10,Candidates!$V$2:$V$201,0))="","",INDEX(Candidates!$R$2:$R$201,MATCH(10,Candidates!$V$2:$V$201,0))),"") -> 46326 | G25: =IF(F25="","",IF(F25<TODAY(),"Overdue by "&(TODAY()-F25)&" days",IF(F25=TODAY(),"Due today","Due in "&(F25-TODAY())&" days"))) -> Due in 26 days | H25: =IFERROR(IF(INDEX(Candidates!$S$2:$S$201,MATCH(10,Candidates!$V$2:$V$201,0))="","",INDEX(Candidates!$S$2:$S$201,MATCH(10,Candidates!$V$2:$V$201,0))),"") | I25: =IFERROR(INDEX(Candidates!$T$2:$T$201,MATCH(10,Candidates!$V$2:$V$201,0))&"","")
A26: =IFERROR(INDEX(Candidates!$A$2:$A$201,MATCH(11,Candidates!$V$2:$V$201,0))&"","") -> CAN-2026-00036 | B26: =IFERROR(INDEX(Candidates!$C$2:$C$201,MATCH(11,Candidates!$V$2:$V$201,0))&"","") -> Christopher Thompson | C26: =IFERROR(INDEX(Candidates!$D$2:$D$201,MATCH(11,Candidates!$V$2:$V$201,0))&"","") -> christopher.thompson@example.com | D26: =IFERROR(INDEX(Candidates!$E$2:$E$201,MATCH(11,Candidates!$V$2:$V$201,0))&"","") -> Software Engineer | E26: =IFERROR(INDEX(Candidates!$N$2:$N$201,MATCH(11,Candidates!$V$2:$V$201,0))&"","") -> Potential Future Fit | F26: =IFERROR(IF(INDEX(Candidates!$R$2:$R$201,MATCH(11,Candidates!$V$2:$V$201,0))="","",INDEX(Candidates!$R$2:$R$201,MATCH(11,Candidates!$V$2:$V$201,0))),"") -> 46297 | G26: =IF(F26="","",IF(F26<TODAY(),"Overdue by "&(TODAY()-F26)&" days",IF(F26=TODAY(),"Due today","Due in "&(F26-TODAY())&" days"))) -> Overdue by 3 days | H26: =IFERROR(IF(INDEX(Candidates!$S$2:$S$201,MATCH(11,Candidates!$V$2:$V$201,0))="","",INDEX(Candidates!$S$2:$S$201,MATCH(11,Candidates!$V$2:$V$201,0))),"") | I26: =IFERROR(INDEX(Candidates!$T$2:$T$201,MATCH(11,Candidates!$V$2:$V$201,0))&"","")
A27: =IFERROR(INDEX(Candidates!$A$2:$A$201,MATCH(12,Candidates!$V$2:$V$201,0))&"","") -> CAN-2026-00037 | B27: =IFERROR(INDEX(Candidates!$C$2:$C$201,MATCH(12,Candidates!$V$2:$V$201,0))&"","") -> Ashley Miller | C27: =IFERROR(INDEX(Candidates!$D$2:$D$201,MATCH(12,Candidates!$V$2:$V$201,0))&"","") -> ashley.miller@example.com | D27: =IFERROR(INDEX(Candidates!$E$2:$E$201,MATCH(12,Candidates!$V$2:$V$201,0))&"","") -> Data Analyst | E27: =IFERROR(INDEX(Candidates!$N$2:$N$201,MATCH(12,Candidates!$V$2:$V$201,0))&"","") -> Potential Future Fit | F27: =IFERROR(IF(INDEX(Candidates!$R$2:$R$201,MATCH(12,Candidates!$V$2:$V$201,0))="","",INDEX(Candidates!$R$2:$R$201,MATCH(12,Candidates!$V$2:$V$201,0))),"") -> 46307 | G27: =IF(F27="","",IF(F27<TODAY(),"Overdue by "&(TODAY()-F27)&" days",IF(F27=TODAY(),"Due today","Due in "&(F27-TODAY())&" days"))) -> Due in 7 days | H27: =IFERROR(IF(INDEX(Candidates!$S$2:$S$201,MATCH(12,Candidates!$V$2:$V$201,0))="","",INDEX(Candidates!$S$2:$S$201,MATCH(12,Candidates!$V$2:$V$201,0))),"") | I27: =IFERROR(INDEX(Candidates!$T$2:$T$201,MATCH(12,Candidates!$V$2:$V$201,0))&"","")
A28: =IFERROR(INDEX(Candidates!$A$2:$A$201,MATCH(13,Candidates!$V$2:$V$201,0))&"","") -> CAN-2026-00040 | B28: =IFERROR(INDEX(Candidates!$C$2:$C$201,MATCH(13,Candidates!$V$2:$V$201,0))&"","") -> Megan Martinez | C28: =IFERROR(INDEX(Candidates!$D$2:$D$201,MATCH(13,Candidates!$V$2:$V$201,0))&"","") -> megan.martinez@example.com | D28: =IFERROR(INDEX(Candidates!$E$2:$E$201,MATCH(13,Candidates!$V$2:$V$201,0))&"","") -> HR Generalist | E28: =IFERROR(INDEX(Candidates!$N$2:$N$201,MATCH(13,Candidates!$V$2:$V$201,0))&"","") -> Strong Future Fit | F28: =IFERROR(IF(INDEX(Candidates!$R$2:$R$201,MATCH(13,Candidates!$V$2:$V$201,0))="","",INDEX(Candidates!$R$2:$R$201,MATCH(13,Candidates!$V$2:$V$201,0))),"") -> 46326 | G28: =IF(F28="","",IF(F28<TODAY(),"Overdue by "&(TODAY()-F28)&" days",IF(F28=TODAY(),"Due today","Due in "&(F28-TODAY())&" days"))) -> Due in 26 days | H28: =IFERROR(IF(INDEX(Candidates!$S$2:$S$201,MATCH(13,Candidates!$V$2:$V$201,0))="","",INDEX(Candidates!$S$2:$S$201,MATCH(13,Candidates!$V$2:$V$201,0))),"") | I28: =IFERROR(INDEX(Candidates!$T$2:$T$201,MATCH(13,Candidates!$V$2:$V$201,0))&"","")
A29: =IFERROR(INDEX(Candidates!$A$2:$A$201,MATCH(14,Candidates!$V$2:$V$201,0))&"","") | B29: =IFERROR(INDEX(Candidates!$C$2:$C$201,MATCH(14,Candidates!$V$2:$V$201,0))&"","") | C29: =IFERROR(INDEX(Candidates!$D$2:$D$201,MATCH(14,Candidates!$V$2:$V$201,0))&"","") | D29: =IFERROR(INDEX(Candidates!$E$2:$E$201,MATCH(14,Candidates!$V$2:$V$201,0))&"","") | E29: =IFERROR(INDEX(Candidates!$N$2:$N$201,MATCH(14,Candidates!$V$2:$V$201,0))&"","") | F29: =IFERROR(IF(INDEX(Candidates!$R$2:$R$201,MATCH(14,Candidates!$V$2:$V$201,0))="","",INDEX(Candidates!$R$2:$R$201,MATCH(14,Candidates!$V$2:$V$201,0))),"") | G29: =IF(F29="","",IF(F29<TODAY(),"Overdue by "&(TODAY()-F29)&" days",IF(F29=TODAY(),"Due today","Due in "&(F29-TODAY())&" days"))) | H29: =IFERROR(IF(INDEX(Candidates!$S$2:$S$201,MATCH(14,Candidates!$V$2:$V$201,0))="","",INDEX(Candidates!$S$2:$S$201,MATCH(14,Candidates!$V$2:$V$201,0))),"") | I29: =IFERROR(INDEX(Candidates!$T$2:$T$201,MATCH(14,Candidates!$V$2:$V$201,0))&"","")
A30: =IFERROR(INDEX(Candidates!$A$2:$A$201,MATCH(15,Candidates!$V$2:$V$201,0))&"","") | B30: =IFERROR(INDEX(Candidates!$C$2:$C$201,MATCH(15,Candidates!$V$2:$V$201,0))&"","") | C30: =IFERROR(INDEX(Candidates!$D$2:$D$201,MATCH(15,Candidates!$V$2:$V$201,0))&"","") | D30: =IFERROR(INDEX(Candidates!$E$2:$E$201,MATCH(15,Candidates!$V$2:$V$201,0))&"","") | E30: =IFERROR(INDEX(Candidates!$N$2:$N$201,MATCH(15,Candidates!$V$2:$V$201,0))&"","") | F30: =IFERROR(IF(INDEX(Candidates!$R$2:$R$201,MATCH(15,Candidates!$V$2:$V$201,0))="","",INDEX(Candidates!$R$2:$R$201,MATCH(15,Candidates!$V$2:$V$201,0))),"") | G30: =IF(F30="","",IF(F30<TODAY(),"Overdue by "&(TODAY()-F30)&" days",IF(F30=TODAY(),"Due today","Due in "&(F30-TODAY())&" days"))) | H30: =IFERROR(IF(INDEX(Candidates!$S$2:$S$201,MATCH(15,Candidates!$V$2:$V$201,0))="","",INDEX(Candidates!$S$2:$S$201,MATCH(15,Candidates!$V$2:$V$201,0))),"") | I30: =IFERROR(INDEX(Candidates!$T$2:$T$201,MATCH(15,Candidates!$V$2:$V$201,0))&"","")
A31: =IFERROR(INDEX(Candidates!$A$2:$A$201,MATCH(16,Candidates!$V$2:$V$201,0))&"","") | B31: =IFERROR(INDEX(Candidates!$C$2:$C$201,MATCH(16,Candidates!$V$2:$V$201,0))&"","") | C31: =IFERROR(INDEX(Candidates!$D$2:$D$201,MATCH(16,Candidates!$V$2:$V$201,0))&"","") | D31: =IFERROR(INDEX(Candidates!$E$2:$E$201,MATCH(16,Candidates!$V$2:$V$201,0))&"","") | E31: =IFERROR(INDEX(Candidates!$N$2:$N$201,MATCH(16,Candidates!$V$2:$V$201,0))&"","") | F31: =IFERROR(IF(INDEX(Candidates!$R$2:$R$201,MATCH(16,Candidates!$V$2:$V$201,0))="","",INDEX(Candidates!$R$2:$R$201,MATCH(16,Candidates!$V$2:$V$201,0))),"") | G31: =IF(F31="","",IF(F31<TODAY(),"Overdue by "&(TODAY()-F31)&" days",IF(F31=TODAY(),"Due today","Due in "&(F31-TODAY())&" days"))) | H31: =IFERROR(IF(INDEX(Candidates!$S$2:$S$201,MATCH(16,Candidates!$V$2:$V$201,0))="","",INDEX(Candidates!$S$2:$S$201,MATCH(16,Candidates!$V$2:$V$201,0))),"") | I31: =IFERROR(INDEX(Candidates!$T$2:$T$201,MATCH(16,Candidates!$V$2:$V$201,0))&"","")
A32: =IFERROR(INDEX(Candidates!$A$2:$A$201,MATCH(17,Candidates!$V$2:$V$201,0))&"","") | B32: =IFERROR(INDEX(Candidates!$C$2:$C$201,MATCH(17,Candidates!$V$2:$V$201,0))&"","") | C32: =IFERROR(INDEX(Candidates!$D$2:$D$201,MATCH(17,Candidates!$V$2:$V$201,0))&"","") | D32: =IFERROR(INDEX(Candidates!$E$2:$E$201,MATCH(17,Candidates!$V$2:$V$201,0))&"","") | E32: =IFERROR(INDEX(Candidates!$N$2:$N$201,MATCH(17,Candidates!$V$2:$V$201,0))&"","") | F32: =IFERROR(IF(INDEX(Candidates!$R$2:$R$201,MATCH(17,Candidates!$V$2:$V$201,0))="","",INDEX(Candidates!$R$2:$R$201,MATCH(17,Candidates!$V$2:$V$201,0))),"") | G32: =IF(F32="","",IF(F32<TODAY(),"Overdue by "&(TODAY()-F32)&" days",IF(F32=TODAY(),"Due today","Due in "&(F32-TODAY())&" days"))) | H32: =IFERROR(IF(INDEX(Candidates!$S$2:$S$201,MATCH(17,Candidates!$V$2:$V$201,0))="","",INDEX(Candidates!$S$2:$S$201,MATCH(17,Candidates!$V$2:$V$201,0))),"") | I32: =IFERROR(INDEX(Candidates!$T$2:$T$201,MATCH(17,Candidates!$V$2:$V$201,0))&"","")
A33: =IFERROR(INDEX(Candidates!$A$2:$A$201,MATCH(18,Candidates!$V$2:$V$201,0))&"","") | B33: =IFERROR(INDEX(Candidates!$C$2:$C$201,MATCH(18,Candidates!$V$2:$V$201,0))&"","") | C33: =IFERROR(INDEX(Candidates!$D$2:$D$201,MATCH(18,Candidates!$V$2:$V$201,0))&"","") | D33: =IFERROR(INDEX(Candidates!$E$2:$E$201,MATCH(18,Candidates!$V$2:$V$201,0))&"","") | E33: =IFERROR(INDEX(Candidates!$N$2:$N$201,MATCH(18,Candidates!$V$2:$V$201,0))&"","") | F33: =IFERROR(IF(INDEX(Candidates!$R$2:$R$201,MATCH(18,Candidates!$V$2:$V$201,0))="","",INDEX(Candidates!$R$2:$R$201,MATCH(18,Candidates!$V$2:$V$201,0))),"") | G33: =IF(F33="","",IF(F33<TODAY(),"Overdue by "&(TODAY()-F33)&" days",IF(F33=TODAY(),"Due today","Due in "&(F33-TODAY())&" days"))) | H33: =IFERROR(IF(INDEX(Candidates!$S$2:$S$201,MATCH(18,Candidates!$V$2:$V$201,0))="","",INDEX(Candidates!$S$2:$S$201,MATCH(18,Candidates!$V$2:$V$201,0))),"") | I33: =IFERROR(INDEX(Candidates!$T$2:$T$201,MATCH(18,Candidates!$V$2:$V$201,0))&"","")
A34: =IFERROR(INDEX(Candidates!$A$2:$A$201,MATCH(19,Candidates!$V$2:$V$201,0))&"","") | B34: =IFERROR(INDEX(Candidates!$C$2:$C$201,MATCH(19,Candidates!$V$2:$V$201,0))&"","") | C34: =IFERROR(INDEX(Candidates!$D$2:$D$201,MATCH(19,Candidates!$V$2:$V$201,0))&"","") | D34: =IFERROR(INDEX(Candidates!$E$2:$E$201,MATCH(19,Candidates!$V$2:$V$201,0))&"","") | E34: =IFERROR(INDEX(Candidates!$N$2:$N$201,MATCH(19,Candidates!$V$2:$V$201,0))&"","") | F34: =IFERROR(IF(INDEX(Candidates!$R$2:$R$201,MATCH(19,Candidates!$V$2:$V$201,0))="","",INDEX(Candidates!$R$2:$R$201,MATCH(19,Candidates!$V$2:$V$201,0))),"") | G34: =IF(F34="","",IF(F34<TODAY(),"Overdue by "&(TODAY()-F34)&" days",IF(F34=TODAY(),"Due today","Due in "&(F34-TODAY())&" days"))) | H34: =IFERROR(IF(INDEX(Candidates!$S$2:$S$201,MATCH(19,Candidates!$V$2:$V$201,0))="","",INDEX(Candidates!$S$2:$S$201,MATCH(19,Candidates!$V$2:$V$201,0))),"") | I34: =IFERROR(INDEX(Candidates!$T$2:$T$201,MATCH(19,Candidates!$V$2:$V$201,0))&"","")
A35: =IFERROR(INDEX(Candidates!$A$2:$A$201,MATCH(20,Candidates!$V$2:$V$201,0))&"","") | B35: =IFERROR(INDEX(Candidates!$C$2:$C$201,MATCH(20,Candidates!$V$2:$V$201,0))&"","") | C35: =IFERROR(INDEX(Candidates!$D$2:$D$201,MATCH(20,Candidates!$V$2:$V$201,0))&"","") | D35: =IFERROR(INDEX(Candidates!$E$2:$E$201,MATCH(20,Candidates!$V$2:$V$201,0))&"","") | E35: =IFERROR(INDEX(Candidates!$N$2:$N$201,MATCH(20,Candidates!$V$2:$V$201,0))&"","") | F35: =IFERROR(IF(INDEX(Candidates!$R$2:$R$201,MATCH(20,Candidates!$V$2:$V$201,0))="","",INDEX(Candidates!$R$2:$R$201,MATCH(20,Candidates!$V$2:$V$201,0))),"") | G35: =IF(F35="","",IF(F35<TODAY(),"Overdue by "&(TODAY()-F35)&" days",IF(F35=TODAY(),"Due today","Due in "&(F35-TODAY())&" days"))) | H35: =IFERROR(IF(INDEX(Candidates!$S$2:$S$201,MATCH(20,Candidates!$V$2:$V$201,0))="","",INDEX(Candidates!$S$2:$S$201,MATCH(20,Candidates!$V$2:$V$201,0))),"") | I35: =IFERROR(INDEX(Candidates!$T$2:$T$201,MATCH(20,Candidates!$V$2:$V$201,0))&"","")

Sheet Find Candidates
A1: Find Candidates for a Vacancy
A2: 🔒 PREMIUM FEATURE · Visible in the demo, locked until you get full access. Message the creator (Start Here tab) to unlock it.
A4: Step 1: choose the vacancy | B4: Marketing Manager | H4: Strong matches (70+) | J4: Possible matches (50-69) | L4: Candidates in pool
H5: =COUNTIF(Match_Calc!$I$2:$I$201,">=70") -> 3 | J5: =COUNTIFS(Match_Calc!$I$2:$I$201,">=50",Match_Calc!$I$2:$I$201,"<70") -> 4 | L5: =COUNTA(Candidates!$A$2:$A$201) -> 40
A6: Department | B6: =IFERROR(INDEX(Positions!$B$2:$B$51,MATCH($B$4,Positions!$C$2:$C$51,0)),"") -> Marketing
A7: Minimum experience (years) | B7: =IFERROR(INDEX(Positions!$D$2:$D$51,MATCH($B$4,Positions!$C$2:$C$51,0)),"") -> 5
A8: Location | B8: =IFERROR(INDEX(Positions!$E$2:$E$51,MATCH($B$4,Positions!$C$2:$C$51,0)),"") -> Denver, CO
A9: Budget: max salary (USD/year) | B9: =IFERROR(INDEX(Positions!$F$2:$F$51,MATCH($B$4,Positions!$C$2:$C$51,0)),"") -> 98000
A10: Required skills | B10: =IFERROR(IF(INDEX(Positions!$G$2:$G$51,MATCH($B$4,Positions!$C$2:$C$51,0))="","",INDEX(Positions!$G$2:$G$51,MATCH($B$4,Positions!$C$2:$C$51,0))),"") -> SEO | C10: =IFERROR(IF(INDEX(Positions!$H$2:$H$51,MATCH($B$4,Positions!$C$2:$C$51,0))="","",INDEX(Positions!$H$2:$H$51,MATCH($B$4,Positions!$C$2:$C$51,0))),"") -> Content Strategy | D10: =IFERROR(IF(INDEX(Positions!$I$2:$I$51,MATCH($B$4,Positions!$C$2:$C$51,0))="","",INDEX(Positions!$I$2:$I$51,MATCH($B$4,Positions!$C$2:$C$51,0))),"") -> Google Analytics | E10: =IFERROR(IF(INDEX(Positions!$J$2:$J$51,MATCH($B$4,Positions!$C$2:$C$51,0))="","",INDEX(Positions!$J$2:$J$51,MATCH($B$4,Positions!$C$2:$C$51,0))),"") -> Email Marketing | F10: =IFERROR(IF(INDEX(Positions!$K$2:$K$51,MATCH($B$4,Positions!$C$2:$C$51,0))="","",INDEX(Positions!$K$2:$K$51,MATCH($B$4,Positions!$C$2:$C$51,0))),"") -> Budgeting
A11: Number of required skills | B11: =SUMPRODUCT(--($B$10:$F$10<>"")) -> 5
A13: 🎯 How the score works (out of 100 points)
A14: Each candidate earns points for each criterion. Add them up and you get the match score. You can change the points in the yellow cells; keep the total at 100.
A15: Skills | B15: 40 | C15: Share of the required skills the candidate has. 4 of 5 skills = 80% of the points.
A16: Experience | B16: 25 | C16: Full points if the candidate has at least the minimum years. Fewer years = a proportion of the points.
A17: Department | B17: 15 | C17: Full points if the candidate applied in the same department as this vacancy.
A18: Location | B18: 10 | C18: Full points if the candidate lives in the same city as the job.
A19: Availability | B19: 5 | C19: Full points if they can start within 30 days, half within 60 days.
A20: Salary | B20: 5 | C20: Full points if their expected salary is within the budget.
A21: Total points (should be 100) | B21: =SUM(B15:B20) -> 100 | C21: =IF(B21=100,"OK","Warning: the total is not 100") -> OK
A22: Rating: 70 or more = Strong match, 50 to 69 = Possible match, below 50 = Weak match. Hired, Do Not Contact and no-consent records are never shown.
A24: ="🏆 Top 10 past candidates for: "&B4 -> 🏆 Top 10 past candidates for: Marketing Manager
A25: Candidate | B25: ID | C25: Applied for | D25: Location | E25: Years exp. | F25: Status | G25: Future potential | H25: Score (0-100) | I25: Match | J25: Rating | K25: Skills pts | L25: Experience pts | M25: Department pts | N25: Location pts | O25: Availability pts | P25: Salary pts | R25: helper: key | S25: helper: row
A26: =IF($S26="","",1&". "&INDEX(Candidates!$C$2:$C$201,$S26)) -> 1. Sarah Martinez | B26: =IF($S26="","",INDEX(Candidates!$A$2:$A$201,$S26)) -> CAN-2026-00023 | C26: =IF($S26="","",INDEX(Candidates!$E$2:$E$201,$S26)) -> Marketing Manager | D26: =IF($S26="","",INDEX(Candidates!$J$2:$J$201,$S26)) -> Atlanta, GA | E26: =IF($S26="","",INDEX(Candidates!$H$2:$H$201,$S26)) -> 6 | F26: =IF($S26="","",INDEX(Candidates!$M$2:$M$201,$S26)) -> Not Selected | G26: =IF($S26="","",INDEX(Candidates!$N$2:$N$201,$S26)) -> Not Currently Relevant | H26: =IF($S26="","",INDEX(Match_Calc!$I$2:$I$201,$S26)) -> 85 | I26: =IF($S26="","",REPT("█",ROUND(H26/10,0))&REPT("░",10-ROUND(H26/10,0))) -> █████████░ | J26: =IF($S26="","",IF(H26>=70,"Strong match",IF(H26>=50,"Possible match","Weak match"))) -> Strong match | K26: =IF($S26="","",INDEX(Match_Calc!$C$2:$C$201,$S26)*$B$15) -> 40 | L26: =IF($S26="","",INDEX(Match_Calc!$D$2:$D$201,$S26)*$B$16) -> 25 | M26: =IF($S26="","",INDEX(Match_Calc!$E$2:$E$201,$S26)*$B$17) -> 15 | N26: =IF($S26="","",INDEX(Match_Calc!$F$2:$F$201,$S26)*$B$18) -> 0 | O26: =IF($S26="","",INDEX(Match_Calc!$G$2:$G$201,$S26)*$B$19) -> 5 | P26: =IF($S26="","",INDEX(Match_Calc!$H$2:$H$201,$S26)*$B$20) -> 0 | R26: =IFERROR(LARGE(Match_Calc!$J$2:$J$201,1),"") -> 85 | S26: =IF(R26="","",MATCH(R26,Match_Calc!$J$2:$J$201,0)) -> 23
A27: =IF($S27="","",2&". "&INDEX(Candidates!$C$2:$C$201,$S27)) -> 2. Nicole Brown | B27: =IF($S27="","",INDEX(Candidates!$A$2:$A$201,$S27)) -> CAN-2026-00007 | C27: =IF($S27="","",INDEX(Candidates!$E$2:$E$201,$S27)) -> Marketing Manager | D27: =IF($S27="","",INDEX(Candidates!$J$2:$J$201,$S27)) -> Atlanta, GA | E27: =IF($S27="","",INDEX(Candidates!$H$2:$H$201,$S27)) -> 5 | F27: =IF($S27="","",INDEX(Candidates!$M$2:$M$201,$S27)) -> Not Selected | G27: =IF($S27="","",INDEX(Candidates!$N$2:$N$201,$S27)) -> Strong Future Fit | H27: =IF($S27="","",INDEX(Match_Calc!$I$2:$I$201,$S27)) -> 82 | I27: =IF($S27="","",REPT("█",ROUND(H27/10,0))&REPT("░",10-ROUND(H27/10,0))) -> ████████░░ | J27: =IF($S27="","",IF(H27>=70,"Strong match",IF(H27>=50,"Possible match","Weak match"))) -> Strong match | K27: =IF($S27="","",INDEX(Match_Calc!$C$2:$C$201,$S27)*$B$15) -> 32 | L27: =IF($S27="","",INDEX(Match_Calc!$D$2:$D$201,$S27)*$B$16) -> 25 | M27: =IF($S27="","",INDEX(Match_Calc!$E$2:$E$201,$S27)*$B$17) -> 15 | N27: =IF($S27="","",INDEX(Match_Calc!$F$2:$F$201,$S27)*$B$18) -> 0 | O27: =IF($S27="","",INDEX(Match_Calc!$G$2:$G$201,$S27)*$B$19) -> 5 | P27: =IF($S27="","",INDEX(Match_Calc!$H$2:$H$201,$S27)*$B$20) -> 5 | R27: =IFERROR(LARGE(Match_Calc!$J$2:$J$201,2),"") -> 82 | S27: =IF(R27="","",MATCH(R27,Match_Calc!$J$2:$J$201,0)) -> 7
A28: =IF($S28="","",3&". "&INDEX(Candidates!$C$2:$C$201,$S28)) -> 3. Ashley Williams | B28: =IF($S28="","",INDEX(Candidates!$A$2:$A$201,$S28)) -> CAN-2026-00009 | C28: =IF($S28="","",INDEX(Candidates!$E$2:$E$201,$S28)) -> Marketing Manager | D28: =IF($S28="","",INDEX(Candidates!$J$2:$J$201,$S28)) -> Austin, TX | E28: =IF($S28="","",INDEX(Candidates!$H$2:$H$201,$S28)) -> 10 | F28: =IF($S28="","",INDEX(Candidates!$M$2:$M$201,$S28)) -> Withdrawn | G28: =IF($S28="","",INDEX(Candidates!$N$2:$N$201,$S28)) -> Not Currently Relevant | H28: =IF($S28="","",INDEX(Match_Calc!$I$2:$I$201,$S28)) -> 82 | I28: =IF($S28="","",REPT("█",ROUND(H28/10,0))&REPT("░",10-ROUND(H28/10,0))) -> ████████░░ | J28: =IF($S28="","",IF(H28>=70,"Strong match",IF(H28>=50,"Possible match","Weak match"))) -> Strong match | K28: =IF($S28="","",INDEX(Match_Calc!$C$2:$C$201,$S28)*$B$15) -> 32 | L28: =IF($S28="","",INDEX(Match_Calc!$D$2:$D$201,$S28)*$B$16) -> 25 | M28: =IF($S28="","",INDEX(Match_Calc!$E$2:$E$201,$S28)*$B$17) -> 15 | N28: =IF($S28="","",INDEX(Match_Calc!$F$2:$F$201,$S28)*$B$18) -> 0 | O28: =IF($S28="","",INDEX(Match_Calc!$G$2:$G$201,$S28)*$B$19) -> 5 | P28: =IF($S28="","",INDEX(Match_Calc!$H$2:$H$201,$S28)*$B$20) -> 5 | R28: =IFERROR(LARGE(Match_Calc!$J$2:$J$201,3),"") -> 82 | S28: =IF(R28="","",MATCH(R28,Match_Calc!$J$2:$J$201,0)) -> 9
A29: =IF($S29="","",4&". "&INDEX(Candidates!$C$2:$C$201,$S29)) -> 4. Jessica Thomas | B29: =IF($S29="","",INDEX(Candidates!$A$2:$A$201,$S29)) -> CAN-2026-00013 | C29: =IF($S29="","",INDEX(Candidates!$E$2:$E$201,$S29)) -> Marketing Manager | D29: =IF($S29="","",INDEX(Candidates!$J$2:$J$201,$S29)) -> Austin, TX | E29: =IF($S29="","",INDEX(Candidates!$H$2:$H$201,$S29)) -> 10 | F29: =IF($S29="","",INDEX(Candidates!$M$2:$M$201,$S29)) -> Not Selected | G29: =IF($S29="","",INDEX(Candidates!$N$2:$N$201,$S29)) -> Potential Future Fit | H29: =IF($S29="","",INDEX(Match_Calc!$I$2:$I$201,$S29)) -> 69 | I29: =IF($S29="","",REPT("█",ROUND(H29/10,0))&REPT("░",10-ROUND(H29/10,0))) -> ███████░░░ | J29: =IF($S29="","",IF(H29>=70,"Strong match",IF(H29>=50,"Possible match","Weak match"))) -> Possible match | K29: =IF($S29="","",INDEX(Match_Calc!$C$2:$C$201,$S29)*$B$15) -> 24 | L29: =IF($S29="","",INDEX(Match_Calc!$D$2:$D$201,$S29)*$B$16) -> 25 | M29: =IF($S29="","",INDEX(Match_Calc!$E$2:$E$201,$S29)*$B$17) -> 15 | N29: =IF($S29="","",INDEX(Match_Calc!$F$2:$F$201,$S29)*$B$18) -> 0 | O29: =IF($S29="","",INDEX(Match_Calc!$G$2:$G$201,$S29)*$B$19) -> 5 | P29: =IF($S29="","",INDEX(Match_Calc!$H$2:$H$201,$S29)*$B$20) -> 0 | R29: =IFERROR(LARGE(Match_Calc!$J$2:$J$201,4),"") -> 69 | S29: =IF(R29="","",MATCH(R29,Match_Calc!$J$2:$J$201,0)) -> 13
A30: =IF($S30="","",5&". "&INDEX(Candidates!$C$2:$C$201,$S30)) -> 5. Ashley Thomas | B30: =IF($S30="","",INDEX(Candidates!$A$2:$A$201,$S30)) -> CAN-2026-00020 | C30: =IF($S30="","",INDEX(Candidates!$E$2:$E$201,$S30)) -> Marketing Manager | D30: =IF($S30="","",INDEX(Candidates!$J$2:$J$201,$S30)) -> Columbus, OH | E30: =IF($S30="","",INDEX(Candidates!$H$2:$H$201,$S30)) -> 3 | F30: =IF($S30="","",INDEX(Candidates!$M$2:$M$201,$S30)) -> Withdrawn | G30: =IF($S30="","",INDEX(Candidates!$N$2:$N$201,$S30)) -> Potential Future Fit | H30: =IF($S30="","",INDEX(Match_Calc!$I$2:$I$201,$S30)) -> 61.5 | I30: =IF($S30="","",REPT("█",ROUND(H30/10,0))&REPT("░",10-ROUND(H30/10,0))) -> ██████░░░░ | J30: =IF($S30="","",IF(H30>=70,"Strong match",IF(H30>=50,"Possible match","Weak match"))) -> Possible match | K30: =IF($S30="","",INDEX(Match_Calc!$C$2:$C$201,$S30)*$B$15) -> 24 | L30: =IF($S30="","",INDEX(Match_Calc!$D$2:$D$201,$S30)*$B$16) -> 15 | M30: =IF($S30="","",INDEX(Match_Calc!$E$2:$E$201,$S30)*$B$17) -> 15 | N30: =IF($S30="","",INDEX(Match_Calc!$F$2:$F$201,$S30)*$B$18) -> 0 | O30: =IF($S30="","",INDEX(Match_Calc!$G$2:$G$201,$S30)*$B$19) -> 2.5 | P30: =IF($S30="","",INDEX(Match_Calc!$H$2:$H$201,$S30)*$B$20) -> 5 | R30: =IFERROR(LARGE(Match_Calc!$J$2:$J$201,5),"") -> 61.5 | S30: =IF(R30="","",MATCH(R30,Match_Calc!$J$2:$J$201,0)) -> 20
A31: =IF($S31="","",6&". "&INDEX(Candidates!$C$2:$C$201,$S31)) -> 6. Ashley Thompson | B31: =IF($S31="","",INDEX(Candidates!$A$2:$A$201,$S31)) -> CAN-2026-00010 | C31: =IF($S31="","",INDEX(Candidates!$E$2:$E$201,$S31)) -> Marketing Manager | D31: =IF($S31="","",INDEX(Candidates!$J$2:$J$201,$S31)) -> Atlanta, GA | E31: =IF($S31="","",INDEX(Candidates!$H$2:$H$201,$S31)) -> 1 | F31: =IF($S31="","",INDEX(Candidates!$M$2:$M$201,$S31)) -> Screened | G31: =IF($S31="","",INDEX(Candidates!$N$2:$N$201,$S31)) -> Strong Future Fit | H31: =IF($S31="","",INDEX(Match_Calc!$I$2:$I$201,$S31)) -> 57 | I31: =IF($S31="","",REPT("█",ROUND(H31/10,0))&REPT("░",10-ROUND(H31/10,0))) -> ██████░░░░ | J31: =IF($S31="","",IF(H31>=70,"Strong match",IF(H31>=50,"Possible match","Weak match"))) -> Possible match | K31: =IF($S31="","",INDEX(Match_Calc!$C$2:$C$201,$S31)*$B$15) -> 32 | L31: =IF($S31="","",INDEX(Match_Calc!$D$2:$D$201,$S31)*$B$16) -> 5 | M31: =IF($S31="","",INDEX(Match_Calc!$E$2:$E$201,$S31)*$B$17) -> 15 | N31: =IF($S31="","",INDEX(Match_Calc!$F$2:$F$201,$S31)*$B$18) -> 0 | O31: =IF($S31="","",INDEX(Match_Calc!$G$2:$G$201,$S31)*$B$19) -> 5 | P31: =IF($S31="","",INDEX(Match_Calc!$H$2:$H$201,$S31)*$B$20) -> 0 | R31: =IFERROR(LARGE(Match_Calc!$J$2:$J$201,6),"") -> 57 | S31: =IF(R31="","",MATCH(R31,Match_Calc!$J$2:$J$201,0)) -> 10
A32: =IF($S32="","",7&". "&INDEX(Candidates!$C$2:$C$201,$S32)) -> 7. Emily Martinez | B32: =IF($S32="","",INDEX(Candidates!$A$2:$A$201,$S32)) -> CAN-2026-00038 | C32: =IF($S32="","",INDEX(Candidates!$E$2:$E$201,$S32)) -> HR Generalist | D32: =IF($S32="","",INDEX(Candidates!$J$2:$J$201,$S32)) -> Denver, CO | E32: =IF($S32="","",INDEX(Candidates!$H$2:$H$201,$S32)) -> 9 | F32: =IF($S32="","",INDEX(Candidates!$M$2:$M$201,$S32)) -> Not Selected | G32: =IF($S32="","",INDEX(Candidates!$N$2:$N$201,$S32)) -> Not Currently Relevant | H32: =IF($S32="","",INDEX(Match_Calc!$I$2:$I$201,$S32)) -> 53 | I32: =IF($S32="","",REPT("█",ROUND(H32/10,0))&REPT("░",10-ROUND(H32/10,0))) -> █████░░░░░ | J32: =IF($S32="","",IF(H32>=70,"Strong match",IF(H32>=50,"Possible match","Weak match"))) -> Possible match | K32: =IF($S32="","",INDEX(Match_Calc!$C$2:$C$201,$S32)*$B$15) -> 8 | L32: =IF($S32="","",INDEX(Match_Calc!$D$2:$D$201,$S32)*$B$16) -> 25 | M32: =IF($S32="","",INDEX(Match_Calc!$E$2:$E$201,$S32)*$B$17) -> 0 | N32: =IF($S32="","",INDEX(Match_Calc!$F$2:$F$201,$S32)*$B$18) -> 10 | O32: =IF($S32="","",INDEX(Match_Calc!$G$2:$G$201,$S32)*$B$19) -> 5 | P32: =IF($S32="","",INDEX(Match_Calc!$H$2:$H$201,$S32)*$B$20) -> 5 | R32: =IFERROR(LARGE(Match_Calc!$J$2:$J$201,7),"") -> 53 | S32: =IF(R32="","",MATCH(R32,Match_Calc!$J$2:$J$201,0)) -> 38
A33: =IF($S33="","",8&". "&INDEX(Candidates!$C$2:$C$201,$S33)) -> 8. Nicole Miller | B33: =IF($S33="","",INDEX(Candidates!$A$2:$A$201,$S33)) -> CAN-2026-00034 | C33: =IF($S33="","",INDEX(Candidates!$E$2:$E$201,$S33)) -> Data Analyst | D33: =IF($S33="","",INDEX(Candidates!$J$2:$J$201,$S33)) -> Columbus, OH | E33: =IF($S33="","",INDEX(Candidates!$H$2:$H$201,$S33)) -> 8 | F33: =IF($S33="","",INDEX(Candidates!$M$2:$M$201,$S33)) -> Not Selected | G33: =IF($S33="","",INDEX(Candidates!$N$2:$N$201,$S33)) -> Strong Future Fit | H33: =IF($S33="","",INDEX(Match_Calc!$I$2:$I$201,$S33)) -> 48.5 | I33: =IF($S33="","",REPT("█",ROUND(H33/10,0))&REPT("░",10-ROUND(H33/10,0))) -> █████░░░░░ | J33: =IF($S33="","",IF(H33>=70,"Strong match",IF(H33>=50,"Possible match","Weak match"))) -> Weak match | K33: =IF($S33="","",INDEX(Match_Calc!$C$2:$C$201,$S33)*$B$15) -> 16 | L33: =IF($S33="","",INDEX(Match_Calc!$D$2:$D$201,$S33)*$B$16) -> 25 | M33: =IF($S33="","",INDEX(Match_Calc!$E$2:$E$201,$S33)*$B$17) -> 0 | N33: =IF($S33="","",INDEX(Match_Calc!$F$2:$F$201,$S33)*$B$18) -> 0 | O33: =IF($S33="","",INDEX(Match_Calc!$G$2:$G$201,$S33)*$B$19) -> 2.5 | P33: =IF($S33="","",INDEX(Match_Calc!$H$2:$H$201,$S33)*$B$20) -> 5 | R33: =IFERROR(LARGE(Match_Calc!$J$2:$J$201,8),"") -> 48.5 | S33: =IF(R33="","",MATCH(R33,Match_Calc!$J$2:$J$201,0)) -> 34
A34: =IF($S34="","",9&". "&INDEX(Candidates!$C$2:$C$201,$S34)) -> 9. Daniel Brown | B34: =IF($S34="","",INDEX(Candidates!$A$2:$A$201,$S34)) -> CAN-2026-00028 | C34: =IF($S34="","",INDEX(Candidates!$E$2:$E$201,$S34)) -> HR Generalist | D34: =IF($S34="","",INDEX(Candidates!$J$2:$J$201,$S34)) -> Dallas, TX | E34: =IF($S34="","",INDEX(Candidates!$H$2:$H$201,$S34)) -> 6 | F34: =IF($S34="","",INDEX(Candidates!$M$2:$M$201,$S34)) -> Withdrawn | G34: =IF($S34="","",INDEX(Candidates!$N$2:$N$201,$S34)) -> Not Currently Relevant | H34: =IF($S34="","",INDEX(Match_Calc!$I$2:$I$201,$S34)) -> 43 | I34: =IF($S34="","",REPT("█",ROUND(H34/10,0))&REPT("░",10-ROUND(H34/10,0))) -> ████░░░░░░ | J34: =IF($S34="","",IF(H34>=70,"Strong match",IF(H34>=50,"Possible match","Weak match"))) -> Weak match | K34: =IF($S34="","",INDEX(Match_Calc!$C$2:$C$201,$S34)*$B$15) -> 8 | L34: =IF($S34="","",INDEX(Match_Calc!$D$2:$D$201,$S34)*$B$16) -> 25 | M34: =IF($S34="","",INDEX(Match_Calc!$E$2:$E$201,$S34)*$B$17) -> 0 | N34: =IF($S34="","",INDEX(Match_Calc!$F$2:$F$201,$S34)*$B$18) -> 0 | O34: =IF($S34="","",INDEX(Match_Calc!$G$2:$G$201,$S34)*$B$19) -> 5 | P34: =IF($S34="","",INDEX(Match_Calc!$H$2:$H$201,$S34)*$B$20) -> 5 | R34: =IFERROR(LARGE(Match_Calc!$J$2:$J$201,9),"") -> 43 | S34: =IF(R34="","",MATCH(R34,Match_Calc!$J$2:$J$201,0)) -> 28
A35: =IF($S35="","",10&". "&INDEX(Candidates!$C$2:$C$201,$S35)) -> 10. Jessica Miller | B35: =IF($S35="","",INDEX(Candidates!$A$2:$A$201,$S35)) -> CAN-2026-00008 | C35: =IF($S35="","",INDEX(Candidates!$E$2:$E$201,$S35)) -> Quality Engineer | D35: =IF($S35="","",INDEX(Candidates!$J$2:$J$201,$S35)) -> Atlanta, GA | E35: =IF($S35="","",INDEX(Candidates!$H$2:$H$201,$S35)) -> 10 | F35: =IF($S35="","",INDEX(Candidates!$M$2:$M$201,$S35)) -> Screened | G35: =IF($S35="","",INDEX(Candidates!$N$2:$N$201,$S35)) -> Potential Future Fit | H35: =IF($S35="","",INDEX(Match_Calc!$I$2:$I$201,$S35)) -> 40.5 | I35: =IF($S35="","",REPT("█",ROUND(H35/10,0))&REPT("░",10-ROUND(H35/10,0))) -> ████░░░░░░ | J35: =IF($S35="","",IF(H35>=70,"Strong match",IF(H35>=50,"Possible match","Weak match"))) -> Weak match | K35: =IF($S35="","",INDEX(Match_Calc!$C$2:$C$201,$S35)*$B$15) -> 8 | L35: =IF($S35="","",INDEX(Match_Calc!$D$2:$D$201,$S35)*$B$16) -> 25 | M35: =IF($S35="","",INDEX(Match_Calc!$E$2:$E$201,$S35)*$B$17) -> 0 | N35: =IF($S35="","",INDEX(Match_Calc!$F$2:$F$201,$S35)*$B$18) -> 0 | O35: =IF($S35="","",INDEX(Match_Calc!$G$2:$G$201,$S35)*$B$19) -> 2.5 | P35: =IF($S35="","",INDEX(Match_Calc!$H$2:$H$201,$S35)*$B$20) -> 5 | R35: =IFERROR(LARGE(Match_Calc!$J$2:$J$201,10),"") -> 40.5 | S35: =IF(R35="","",MATCH(R35,Match_Calc!$J$2:$J$201,0)) -> 8

Sheet Positions
A1: Position ID | B1: Department | C1: Position Title | D1: Min. Experience (yrs) | E1: Location | F1: Max Salary (USD/year) | G1: Skill 1 | H1: Skill 2 | I1: Skill 3 | J1: Skill 4 | K1: Skill 5 | L1: Status | M1: Openings (#) | N1: Date Opened | O1: Hiring Manager | P1: Priority | Q1: open # (helper) | S1: Add a new position in the next empty row (up to row 51). Only positions with Status = Open are counted on the Dashboard.
A2: POS-001 | B2: Operations | C2: Operations Manager | D2: 5 | E2: Chicago, IL | F2: 105000 | G2: Process Improvement | H2: Lean Six Sigma | I2: Budgeting | J2: Team Leadership | K2: Supply Chain | L2: Open | M2: 1 | N2: 46273 | O2: Karen Mitchell | P2: High | Q2: =IF(AND(A2<>"",L2="Open"),COUNTIF($L$2:L2,"Open"),"") -> 1
A3: POS-002 | B3: Analytics | C3: Data Analyst | D3: 2 | E3: Austin, TX | F3: 85000 | G3: SQL | H3: Excel | I3: Tableau | J3: Python | K3: Reporting | L3: Open | M3: 2 | N3: 46280 | O3: David Brooks | P3: Medium | Q3: =IF(AND(A3<>"",L3="Open"),COUNTIF($L$2:L3,"Open"),"") -> 2
A4: POS-003 | B4: Human Resources | C4: HR Generalist | D4: 3 | E4: Atlanta, GA | F4: 72000 | G4: Recruiting | H4: Employee Relations | I4: HRIS | J4: Onboarding | K4: Benefits Administration | L4: Open | M4: 1 | N4: 46287 | O4: Linda Foster | P4: Medium | Q4: =IF(AND(A4<>"",L4="Open"),COUNTIF($L$2:L4,"Open"),"") -> 3
A5: POS-004 | B5: Finance | C5: Staff Accountant | D5: 2 | E5: Columbus, OH | F5: 68000 | G5: GAAP | H5: QuickBooks | I5: Accounts Payable | J5: Excel | K5: Reconciliation | L5: Closed | M5: 1 | N5: 46244 | O5: Robert Hayes | P5: Low | Q5: =IF(AND(A5<>"",L5="Open"),COUNTIF($L$2:L5,"Open"),"")
A6: POS-005 | B6: Sales | C6: Account Executive | D6: 3 | E6: Dallas, TX | F6: 95000 | G6: Salesforce | H6: CRM | I6: Negotiation | J6: B2B Sales | K6: Pipeline Management | L6: Open | M6: 3 | N6: 46266 | O6: Steven Parker | P6: High | Q6: =IF(AND(A6<>"",L6="Open"),COUNTIF($L$2:L6,"Open"),"") -> 4
A7: POS-006 | B7: Marketing | C7: Marketing Manager | D7: 5 | E7: Denver, CO | F7: 98000 | G7: SEO | H7: Content Strategy | I7: Google Analytics | J7: Email Marketing | K7: Budgeting | L7: Open | M7: 1 | N7: 46294 | O7: Michelle Reed | P7: Medium | Q7: =IF(AND(A7<>"",L7="Open"),COUNTIF($L$2:L7,"Open"),"") -> 5
A8: POS-007 | B8: Engineering | C8: Quality Engineer | D8: 3 | E8: Columbus, OH | F8: 90000 | G8: ISO 9001 | H8: Root Cause Analysis | I8: FMEA | J8: SPC | K8: Internal Audit | L8: On Hold | M8: 1 | N8: 46259 | O8: James Turner | P8: Low | Q8: =IF(AND(A8<>"",L8="Open"),COUNTIF($L$2:L8,"Open"),"")
A9: POS-008 | B9: Engineering | C9: Software Engineer | D9: 3 | E9: Austin, TX | F9: 130000 | G9: Python | H9: JavaScript | I9: SQL | J9: Git | K9: AWS | L9: Open | M9: 2 | N9: 46282 | O9: Patricia Collins | P9: High | Q9: =IF(AND(A9<>"",L9="Open"),COUNTIF($L$2:L9,"Open"),"") -> 6
Q10: =IF(AND(A10<>"",L10="Open"),COUNTIF($L$2:L10,"Open"),"")
Q11: =IF(AND(A11<>"",L11="Open"),COUNTIF($L$2:L11,"Open"),"")
Q12: =IF(AND(A12<>"",L12="Open"),COUNTIF($L$2:L12,"Open"),"")
Q13: =IF(AND(A13<>"",L13="Open"),COUNTIF($L$2:L13,"Open"),"")
Q14: =IF(AND(A14<>"",L14="Open"),COUNTIF($L$2:L14,"Open"),"")
Q15: =IF(AND(A15<>"",L15="Open"),COUNTIF($L$2:L15,"Open"),"")
Q16: =IF(AND(A16<>"",L16="Open"),COUNTIF($L$2:L16,"Open"),"")
Q17: =IF(AND(A17<>"",L17="Open"),COUNTIF($L$2:L17,"Open"),"")
Q18: =IF(AND(A18<>"",L18="Open"),COUNTIF($L$2:L18,"Open"),"")
Q19: =IF(AND(A19<>"",L19="Open"),COUNTIF($L$2:L19,"Open"),"")
Q20: =IF(AND(A20<>"",L20="Open"),COUNTIF($L$2:L20,"Open"),"")
Q21: =IF(AND(A21<>"",L21="Open"),COUNTIF($L$2:L21,"Open"),"")
... Q51: =IF(AND(A51<>"",L51="Open"),COUNTIF($L$2:L51,"Open"),"")

Sheet Contact Log
A1: Contact Date | B1: Candidate ID | C1: Name | D1: Outcome | E1: Notes | F1: Next Follow-up Date | G1: Logged At | I1: 🔒 PREMIUM FEATURE: filled automatically by the Follow-Up tool in the full version.
A2: 46293 | B2: CAN-2026-00001 | C2: Jason Martinez | D2: Interested | E2: Initial contact | F2: 46361 | G2: 46285
A3: 46293 | B3: CAN-2026-00004 | C3: Ashley Martinez | D3: Interested | E3: Initial contact | F3: 46387 | G3: 46285
A4: 46285 | B4: CAN-2026-00005 | C4: Joshua Martinez | D4: No response | E4: Initial contact | F4: 46386 | G4: 46285
A5: 46289 | B5: CAN-2026-00007 | C5: Nicole Brown | D5: Interested | E5: Initial contact | F5: 46311 | G5: 46285
A6: 46285 | B6: CAN-2026-00010 | C6: Ashley Thompson | D6: Interested | E6: Initial contact | F6: 46371 | G6: 46285

Sheet Match_Calc
A1: Candidate ID | B1: Eligible (1/0) | C1: Skills (0-1) | D1: Experience (0-1) | E1: Department (0-1) | F1: Location (0-1) | G1: Availability (0-1) | H1: Salary (0-1) | I1: Score (points) | J1: Sort key | L1: Calculation tab. Do not edit.
A2: =IF(Candidates!A2="","",Candidates!A2) -> CAN-2026-00001 | B2: =IF(Candidates!A2="","",IF(AND(Candidates!M2<>"Hired",Candidates!N2<>"Do Not Contact",Candidates!Q2="Yes"),1,0)) -> 0 | C2: =IF($B2<>1,"",IF('Find Candidates'!$B$11=0,0,SUMPRODUCT(('Find Candidates'!$B$10:$F$10<>"")*ISNUMBER(SEARCH('Find Candidates'!$B$10:$F$10,Candidates!G2)))/'Find Candidates'!$B$11)) | D2: =IF($B2<>1,"",IF(N('Find Candidates'!$B$7)=0,1,MIN(1,Candidates!H2/'Find Candidates'!$B$7))) | E2: =IF($B2<>1,"",IF(Candidates!F2='Find Candidates'!$B$6,1,0)) | F2: =IF($B2<>1,"",IF(Candidates!J2='Find Candidates'!$B$8,1,0)) | G2: =IF($B2<>1,"",IF(Candidates!K2<=30,1,IF(Candidates!K2<=60,0.5,0))) | H2: =IF($B2<>1,"",IF(Candidates!I2<='Find Candidates'!$B$9,1,0)) | I2: =IF($B2=1,C2*'Find Candidates'!$B$15+D2*'Find Candidates'!$B$16+E2*'Find Candidates'!$B$17+F2*'Find Candidates'!$B$18+G2*'Find Candidates'!$B$19+H2*'Find Candidates'!$B$20,0) -> 0 | J2: =IF(AND($B2=1,I2>0),I2-ROW()/10^8,"")
A3: =IF(Candidates!A3="","",Candidates!A3) -> CAN-2026-00002 | B3: =IF(Candidates!A3="","",IF(AND(Candidates!M3<>"Hired",Candidates!N3<>"Do Not Contact",Candidates!Q3="Yes"),1,0)) -> 0 | C3: =IF($B3<>1,"",IF('Find Candidates'!$B$11=0,0,SUMPRODUCT(('Find Candidates'!$B$10:$F$10<>"")*ISNUMBER(SEARCH('Find Candidates'!$B$10:$F$10,Candidates!G3)))/'Find Candidates'!$B$11)) | D3: =IF($B3<>1,"",IF(N('Find Candidates'!$B$7)=0,1,MIN(1,Candidates!H3/'Find Candidates'!$B$7))) | E3: =IF($B3<>1,"",IF(Candidates!F3='Find Candidates'!$B$6,1,0)) | F3: =IF($B3<>1,"",IF(Candidates!J3='Find Candidates'!$B$8,1,0)) | G3: =IF($B3<>1,"",IF(Candidates!K3<=30,1,IF(Candidates!K3<=60,0.5,0))) | H3: =IF($B3<>1,"",IF(Candidates!I3<='Find Candidates'!$B$9,1,0)) | I3: =IF($B3=1,C3*'Find Candidates'!$B$15+D3*'Find Candidates'!$B$16+E3*'Find Candidates'!$B$17+F3*'Find Candidates'!$B$18+G3*'Find Candidates'!$B$19+H3*'Find Candidates'!$B$20,0) -> 0 | J3: =IF(AND($B3=1,I3>0),I3-ROW()/10^8,"")
A4: =IF(Candidates!A4="","",Candidates!A4) -> CAN-2026-00003 | B4: =IF(Candidates!A4="","",IF(AND(Candidates!M4<>"Hired",Candidates!N4<>"Do Not Contact",Candidates!Q4="Yes"),1,0)) -> 0 | C4: =IF($B4<>1,"",IF('Find Candidates'!$B$11=0,0,SUMPRODUCT(('Find Candidates'!$B$10:$F$10<>"")*ISNUMBER(SEARCH('Find Candidates'!$B$10:$F$10,Candidates!G4)))/'Find Candidates'!$B$11)) | D4: =IF($B4<>1,"",IF(N('Find Candidates'!$B$7)=0,1,MIN(1,Candidates!H4/'Find Candidates'!$B$7))) | E4: =IF($B4<>1,"",IF(Candidates!F4='Find Candidates'!$B$6,1,0)) | F4: =IF($B4<>1,"",IF(Candidates!J4='Find Candidates'!$B$8,1,0)) | G4: =IF($B4<>1,"",IF(Candidates!K4<=30,1,IF(Candidates!K4<=60,0.5,0))) | H4: =IF($B4<>1,"",IF(Candidates!I4<='Find Candidates'!$B$9,1,0)) | I4: =IF($B4=1,C4*'Find Candidates'!$B$15+D4*'Find Candidates'!$B$16+E4*'Find Candidates'!$B$17+F4*'Find Candidates'!$B$18+G4*'Find Candidates'!$B$19+H4*'Find Candidates'!$B$20,0) -> 0 | J4: =IF(AND($B4=1,I4>0),I4-ROW()/10^8,"")
A5: =IF(Candidates!A5="","",Candidates!A5) -> CAN-2026-00004 | B5: =IF(Candidates!A5="","",IF(AND(Candidates!M5<>"Hired",Candidates!N5<>"Do Not Contact",Candidates!Q5="Yes"),1,0)) -> 1 | C5: =IF($B5<>1,"",IF('Find Candidates'!$B$11=0,0,SUMPRODUCT(('Find Candidates'!$B$10:$F$10<>"")*ISNUMBER(SEARCH('Find Candidates'!$B$10:$F$10,Candidates!G5)))/'Find Candidates'!$B$11)) -> 0 | D5: =IF($B5<>1,"",IF(N('Find Candidates'!$B$7)=0,1,MIN(1,Candidates!H5/'Find Candidates'!$B$7))) -> 0.4 | E5: =IF($B5<>1,"",IF(Candidates!F5='Find Candidates'!$B$6,1,0)) -> 0 | F5: =IF($B5<>1,"",IF(Candidates!J5='Find Candidates'!$B$8,1,0)) -> 0 | G5: =IF($B5<>1,"",IF(Candidates!K5<=30,1,IF(Candidates!K5<=60,0.5,0))) -> 1 | H5: =IF($B5<>1,"",IF(Candidates!I5<='Find Candidates'!$B$9,1,0)) -> 0 | I5: =IF($B5=1,C5*'Find Candidates'!$B$15+D5*'Find Candidates'!$B$16+E5*'Find Candidates'!$B$17+F5*'Find Candidates'!$B$18+G5*'Find Candidates'!$B$19+H5*'Find Candidates'!$B$20,0) -> 15 | J5: =IF(AND($B5=1,I5>0),I5-ROW()/10^8,"") -> 15
A6: =IF(Candidates!A6="","",Candidates!A6) -> CAN-2026-00005 | B6: =IF(Candidates!A6="","",IF(AND(Candidates!M6<>"Hired",Candidates!N6<>"Do Not Contact",Candidates!Q6="Yes"),1,0)) -> 1 | C6: =IF($B6<>1,"",IF('Find Candidates'!$B$11=0,0,SUMPRODUCT(('Find Candidates'!$B$10:$F$10<>"")*ISNUMBER(SEARCH('Find Candidates'!$B$10:$F$10,Candidates!G6)))/'Find Candidates'!$B$11)) -> 0 | D6: =IF($B6<>1,"",IF(N('Find Candidates'!$B$7)=0,1,MIN(1,Candidates!H6/'Find Candidates'!$B$7))) -> 0.4 | E6: =IF($B6<>1,"",IF(Candidates!F6='Find Candidates'!$B$6,1,0)) -> 0 | F6: =IF($B6<>1,"",IF(Candidates!J6='Find Candidates'!$B$8,1,0)) -> 1 | G6: =IF($B6<>1,"",IF(Candidates!K6<=30,1,IF(Candidates!K6<=60,0.5,0))) -> 1 | H6: =IF($B6<>1,"",IF(Candidates!I6<='Find Candidates'!$B$9,1,0)) -> 1 | I6: =IF($B6=1,C6*'Find Candidates'!$B$15+D6*'Find Candidates'!$B$16+E6*'Find Candidates'!$B$17+F6*'Find Candidates'!$B$18+G6*'Find Candidates'!$B$19+H6*'Find Candidates'!$B$20,0) -> 30 | J6: =IF(AND($B6=1,I6>0),I6-ROW()/10^8,"") -> 30
A7: =IF(Candidates!A7="","",Candidates!A7) -> CAN-2026-00006 | B7: =IF(Candidates!A7="","",IF(AND(Candidates!M7<>"Hired",Candidates!N7<>"Do Not Contact",Candidates!Q7="Yes"),1,0)) -> 0 | C7: =IF($B7<>1,"",IF('Find Candidates'!$B$11=0,0,SUMPRODUCT(('Find Candidates'!$B$10:$F$10<>"")*ISNUMBER(SEARCH('Find Candidates'!$B$10:$F$10,Candidates!G7)))/'Find Candidates'!$B$11)) | D7: =IF($B7<>1,"",IF(N('Find Candidates'!$B$7)=0,1,MIN(1,Candidates!H7/'Find Candidates'!$B$7))) | E7: =IF($B7<>1,"",IF(Candidates!F7='Find Candidates'!$B$6,1,0)) | F7: =IF($B7<>1,"",IF(Candidates!J7='Find Candidates'!$B$8,1,0)) | G7: =IF($B7<>1,"",IF(Candidates!K7<=30,1,IF(Candidates!K7<=60,0.5,0))) | H7: =IF($B7<>1,"",IF(Candidates!I7<='Find Candidates'!$B$9,1,0)) | I7: =IF($B7=1,C7*'Find Candidates'!$B$15+D7*'Find Candidates'!$B$16+E7*'Find Candidates'!$B$17+F7*'Find Candidates'!$B$18+G7*'Find Candidates'!$B$19+H7*'Find Candidates'!$B$20,0) -> 0 | J7: =IF(AND($B7=1,I7>0),I7-ROW()/10^8,"")
A8: =IF(Candidates!A8="","",Candidates!A8) -> CAN-2026-00007 | B8: =IF(Candidates!A8="","",IF(AND(Candidates!M8<>"Hired",Candidates!N8<>"Do Not Contact",Candidates!Q8="Yes"),1,0)) -> 1 | C8: =IF($B8<>1,"",IF('Find Candidates'!$B$11=0,0,SUMPRODUCT(('Find Candidates'!$B$10:$F$10<>"")*ISNUMBER(SEARCH('Find Candidates'!$B$10:$F$10,Candidates!G8)))/'Find Candidates'!$B$11)) -> 0.8 | D8: =IF($B8<>1,"",IF(N('Find Candidates'!$B$7)=0,1,MIN(1,Candidates!H8/'Find Candidates'!$B$7))) -> 1 | E8: =IF($B8<>1,"",IF(Candidates!F8='Find Candidates'!$B$6,1,0)) -> 1 | F8: =IF($B8<>1,"",IF(Candidates!J8='Find Candidates'!$B$8,1,0)) -> 0 | G8: =IF($B8<>1,"",IF(Candidates!K8<=30,1,IF(Candidates!K8<=60,0.5,0))) -> 1 | H8: =IF($B8<>1,"",IF(Candidates!I8<='Find Candidates'!$B$9,1,0)) -> 1 | I8: =IF($B8=1,C8*'Find Candidates'!$B$15+D8*'Find Candidates'!$B$16+E8*'Find Candidates'!$B$17+F8*'Find Candidates'!$B$18+G8*'Find Candidates'!$B$19+H8*'Find Candidates'!$B$20,0) -> 82 | J8: =IF(AND($B8=1,I8>0),I8-ROW()/10^8,"") -> 82
A9: =IF(Candidates!A9="","",Candidates!A9) -> CAN-2026-00008 | B9: =IF(Candidates!A9="","",IF(AND(Candidates!M9<>"Hired",Candidates!N9<>"Do Not Contact",Candidates!Q9="Yes"),1,0)) -> 1 | C9: =IF($B9<>1,"",IF('Find Candidates'!$B$11=0,0,SUMPRODUCT(('Find Candidates'!$B$10:$F$10<>"")*ISNUMBER(SEARCH('Find Candidates'!$B$10:$F$10,Candidates!G9)))/'Find Candidates'!$B$11)) -> 0.2 | D9: =IF($B9<>1,"",IF(N('Find Candidates'!$B$7)=0,1,MIN(1,Candidates!H9/'Find Candidates'!$B$7))) -> 1 | E9: =IF($B9<>1,"",IF(Candidates!F9='Find Candidates'!$B$6,1,0)) -> 0 | F9: =IF($B9<>1,"",IF(Candidates!J9='Find Candidates'!$B$8,1,0)) -> 0 | G9: =IF($B9<>1,"",IF(Candidates!K9<=30,1,IF(Candidates!K9<=60,0.5,0))) -> 0.5 | H9: =IF($B9<>1,"",IF(Candidates!I9<='Find Candidates'!$B$9,1,0)) -> 1 | I9: =IF($B9=1,C9*'Find Candidates'!$B$15+D9*'Find Candidates'!$B$16+E9*'Find Candidates'!$B$17+F9*'Find Candidates'!$B$18+G9*'Find Candidates'!$B$19+H9*'Find Candidates'!$B$20,0) -> 40.5 | J9: =IF(AND($B9=1,I9>0),I9-ROW()/10^8,"") -> 40.5
A10: =IF(Candidates!A10="","",Candidates!A10) -> CAN-2026-00009 | B10: =IF(Candidates!A10="","",IF(AND(Candidates!M10<>"Hired",Candidates!N10<>"Do Not Contact",Candidates!Q10="Yes"),1,0)) -> 1 | C10: =IF($B10<>1,"",IF('Find Candidates'!$B$11=0,0,SUMPRODUCT(('Find Candidates'!$B$10:$F$10<>"")*ISNUMBER(SEARCH('Find Candidates'!$B$10:$F$10,Candidates!G10)))/'Find Candidates'!$B$11)) -> 0.8 | D10: =IF($B10<>1,"",IF(N('Find Candidates'!$B$7)=0,1,MIN(1,Candidates!H10/'Find Candidates'!$B$7))) -> 1 | E10: =IF($B10<>1,"",IF(Candidates!F10='Find Candidates'!$B$6,1,0)) -> 1 | F10: =IF($B10<>1,"",IF(Candidates!J10='Find Candidates'!$B$8,1,0)) -> 0 | G10: =IF($B10<>1,"",IF(Candidates!K10<=30,1,IF(Candidates!K10<=60,0.5,0))) -> 1 | H10: =IF($B10<>1,"",IF(Candidates!I10<='Find Candidates'!$B$9,1,0)) -> 1 | I10: =IF($B10=1,C10*'Find Candidates'!$B$15+D10*'Find Candidates'!$B$16+E10*'Find Candidates'!$B$17+F10*'Find Candidates'!$B$18+G10*'Find Candidates'!$B$19+H10*'Find Candidates'!$B$20,0) -> 82 | J10: =IF(AND($B10=1,I10>0),I10-ROW()/10^8,"") -> 82
A11: =IF(Candidates!A11="","",Candidates!A11) -> CAN-2026-00010 | B11: =IF(Candidates!A11="","",IF(AND(Candidates!M11<>"Hired",Candidates!N11<>"Do Not Contact",Candidates!Q11="Yes"),1,0)) -> 1 | C11: =IF($B11<>1,"",IF('Find Candidates'!$B$11=0,0,SUMPRODUCT(('Find Candidates'!$B$10:$F$10<>"")*ISNUMBER(SEARCH('Find Candidates'!$B$10:$F$10,Candidates!G11)))/'Find Candidates'!$B$11)) -> 0.8 | D11: =IF($B11<>1,"",IF(N('Find Candidates'!$B$7)=0,1,MIN(1,Candidates!H11/'Find Candidates'!$B$7))) -> 0.2 | E11: =IF($B11<>1,"",IF(Candidates!F11='Find Candidates'!$B$6,1,0)) -> 1 | F11: =IF($B11<>1,"",IF(Candidates!J11='Find Candidates'!$B$8,1,0)) -> 0 | G11: =IF($B11<>1,"",IF(Candidates!K11<=30,1,IF(Candidates!K11<=60,0.5,0))) -> 1 | H11: =IF($B11<>1,"",IF(Candidates!I11<='Find Candidates'!$B$9,1,0)) -> 0 | I11: =IF($B11=1,C11*'Find Candidates'!$B$15+D11*'Find Candidates'!$B$16+E11*'Find Candidates'!$B$17+F11*'Find Candidates'!$B$18+G11*'Find Candidates'!$B$19+H11*'Find Candidates'!$B$20,0) -> 57 | J11: =IF(AND($B11=1,I11>0),I11-ROW()/10^8,"") -> 57
A12: =IF(Candidates!A12="","",Candidates!A12) -> CAN-2026-00011 | B12: =IF(Candidates!A12="","",IF(AND(Candidates!M12<>"Hired",Candidates!N12<>"Do Not Contact",Candidates!Q12="Yes"),1,0)) -> 1 | C12: =IF($B12<>1,"",IF('Find Candidates'!$B$11=0,0,SUMPRODUCT(('Find Candidates'!$B$10:$F$10<>"")*ISNUMBER(SEARCH('Find Candidates'!$B$10:$F$10,Candidates!G12)))/'Find Candidates'!$B$11)) -> 0 | D12: =IF($B12<>1,"",IF(N('Find Candidates'!$B$7)=0,1,MIN(1,Candidates!H12/'Find Candidates'!$B$7))) -> 1 | E12: =IF($B12<>1,"",IF(Candidates!F12='Find Candidates'!$B$6,1,0)) -> 0 | F12: =IF($B12<>1,"",IF(Candidates!J12='Find Candidates'!$B$8,1,0)) -> 0 | G12: =IF($B12<>1,"",IF(Candidates!K12<=30,1,IF(Candidates!K12<=60,0.5,0))) -> 0.5 | H12: =IF($B12<>1,"",IF(Candidates!I12<='Find Candidates'!$B$9,1,0)) -> 1 | I12: =IF($B12=1,C12*'Find Candidates'!$B$15+D12*'Find Candidates'!$B$16+E12*'Find Candidates'!$B$17+F12*'Find Candidates'!$B$18+G12*'Find Candidates'!$B$19+H12*'Find Candidates'!$B$20,0) -> 32.5 | J12: =IF(AND($B12=1,I12>0),I12-ROW()/10^8,"") -> 32.5
A13: =IF(Candidates!A13="","",Candidates!A13) -> CAN-2026-00012 | B13: =IF(Candidates!A13="","",IF(AND(Candidates!M13<>"Hired",Candidates!N13<>"Do Not Contact",Candidates!Q13="Yes"),1,0)) -> 1 | C13: =IF($B13<>1,"",IF('Find Candidates'!$B$11=0,0,SUMPRODUCT(('Find Candidates'!$B$10:$F$10<>"")*ISNUMBER(SEARCH('Find Candidates'!$B$10:$F$10,Candidates!G13)))/'Find Candidates'!$B$11)) -> 0 | D13: =IF($B13<>1,"",IF(N('Find Candidates'!$B$7)=0,1,MIN(1,Candidates!H13/'Find Candidates'!$B$7))) -> 1 | E13: =IF($B13<>1,"",IF(Candidates!F13='Find Candidates'!$B$6,1,0)) -> 0 | F13: =IF($B13<>1,"",IF(Candidates!J13='Find Candidates'!$B$8,1,0)) -> 0 | G13: =IF($B13<>1,"",IF(Candidates!K13<=30,1,IF(Candidates!K13<=60,0.5,0))) -> 1 | H13: =IF($B13<>1,"",IF(Candidates!I13<='Find Candidates'!$B$9,1,0)) -> 1 | I13: =IF($B13=1,C13*'Find Candidates'!$B$15+D13*'Find Candidates'!$B$16+E13*'Find Candidates'!$B$17+F13*'Find Candidates'!$B$18+G13*'Find Candidates'!$B$19+H13*'Find Candidates'!$B$20,0) -> 35 | J13: =IF(AND($B13=1,I13>0),I13-ROW()/10^8,"") -> 35
... A201: =IF(Candidates!A201="","",Candidates!A201) | B201: =IF(Candidates!A201="","",IF(AND(Candidates!M201<>"Hired",Candidates!N201<>"Do Not Contact",Candidates!Q201="Yes"),1,0)) | C201: =IF($B201<>1,"",IF('Find Candidates'!$B$11=0,0,SUMPRODUCT(('Find Candidates'!$B$10:$F$10<>"")*ISNUMBER(SEARCH('Find Candidates'!$B$10:$F$10,Candidates!G201)))/'Find Candidates'!$B$11)) | D201: =IF($B201<>1,"",IF(N('Find Candidates'!$B$7)=0,1,MIN(1,Candidates!H201/'Find Candidates'!$B$7))) | E201: =IF($B201<>1,"",IF(Candidates!F201='Find Candidates'!$B$6,1,0)) | F201: =IF($B201<>1,"",IF(Candidates!J201='Find Candidates'!$B$8,1,0)) | G201: =IF($B201<>1,"",IF(Candidates!K201<=30,1,IF(Candidates!K201<=60,0.5,0))) | H201: =IF($B201<>1,"",IF(Candidates!I201<='Find Candidates'!$B$9,1,0)) | I201: =IF($B201=1,C201*'Find Candidates'!$B$15+D201*'Find Candidates'!$B$16+E201*'Find Candidates'!$B$17+F201*'Find Candidates'!$B$18+G201*'Find Candidates'!$B$19+H201*'Find Candidates'!$B$20,0) -> 0 | J201: =IF(AND($B201=1,I201>0),I201-ROW()/10^8,"")

Sheet Lists
A1: Departments | B1: Recruitment Status | C1: Future Potential | D1: Source | E1: Yes/No | F1: Locations | G1: Skills | H1: Follow-up Outcome | I1: Position Status | J1: Priority | L1: Edit these lists to change the dropdowns everywhere. Add new skills at the bottom of the Skills column.
A2: Operations | B2: Applied | C2: Strong Future Fit | D2: LinkedIn | E2: Yes | F2: Chicago, IL | G2: AWS | H2: Interested | I2: Open | J2: High
A3: Analytics | B3: Screened | C3: Potential Future Fit | D3: Indeed | E3: No | F3: Austin, TX | G3: Accounts Payable | H3: Not interested | I3: On Hold | J3: Medium
A4: Human Resources | B4: Interviewed | C4: Not Currently Relevant | D4: Referral | F4: Atlanta, GA | G4: B2B Sales | H4: No response | I4: Closed | J4: Low
A5: Finance | B5: Offered | C5: Do Not Contact | D5: Company Website | F5: Columbus, OH | G5: Benefits Administration | H5: Hired elsewhere
A6: Sales | B6: Hired | D6: Staffing Agency | F6: Dallas, TX | G6: Budgeting | H6: Do not contact again
A7: Marketing | B7: Not Selected | F7: Denver, CO | G7: CRM
A8: Engineering | B8: Withdrawn | G8: Content Strategy
G9: Email Marketing
G10: Employee Relations
G11: Excel
G12: FMEA
G13: GAAP
G14: Git
G15: Google Analytics
G16: HRIS
G17: ISO 9001
G18: Internal Audit
G19: JavaScript
G20: Lean Six Sigma
... G37: Team Leadership

Sheet Settings
A1: Setting | B1: Value (edit here, it appears on Start Here)
A2: Your name | B2: Mohammad Zargar
A3: Your title | B3: Process Improvement & Business Systems
A4: LinkedIn URL | B4: https://linkedin.com/mohammad-zargar
A5: Email | B5: s.mohammad.zargar@gmail.com
A6: Email subject | B6: Full access request: Candidate Talent Pool
A7: Licensed to | B7: Demo copy, not licensed for business use
A8: Edition | B8: Demo
